{"content":[{"ordem":1,"produto":{"codigo":7332,"nome":"AEROFRIN","numeroRegistro":"117170009","tipo":{"codigo":1,"descricao":null},"categoria":null,"situacaoRotulo":null,"dataVencimento":null,"mesAnoVencimento":"062029","dataVencimentoRegistro":"2029-06-01T00:00:00.000-0300","principioAtivo":"SULFATO DE SALBUTAMOL MICRONIZADO","situacaoApresentacao":"Válido","dataRegistro":"1999-06-14T00:00:00.000-0300","categoriaRegulatoria":{"codigo":8,"descricao":"Similar"},"medicamentoReferencia":null,"categoriaProduto":null,"tipoAutorizacao":"REGISTRADO","numeroRegistroFormatado":"117170009","mesAnoVencimentoFormatado":"06/2029","acancelar":false},"empresa":{"cnpj":"25773037000183","razaoSocial":"PHARMASCIENCE INDUSTRIA FARMACEUTICA S.A","numeroAutorizacao":"1017173","cnpjFormatado":"25.773.037/0001-83"},"processo":{"numero":"250000164699804","situacao":29,"numeroProcessoFormatado":"25000.016469/98-04"}},{"ordem":2,"produto":{"codigo":6181,"nome":"AFTODERM","numeroRegistro":"117170016","tipo":{"codigo":1,"descricao":null},"categoria":null,"situacaoRotulo":null,"dataVencimento":null,"mesAnoVencimento":"022010","dataVencimentoRegistro":"2010-02-01T00:00:00.000-0300","principioAtivo":null,"situacaoApresentacao":"Caduco/Cancelado","dataRegistro":"2000-02-24T00:00:00.000-0200","categoriaRegulatoria":{"codigo":8,"descricao":"Similar"},"medicamentoReferencia":null,"categoriaProduto":null,"tipoAutorizacao":"REGISTRADO","numeroRegistroFormatado":"117170016","mesAnoVencimentoFormatado":"02/2010","acancelar":false},"empresa":{"cnpj":"25773037000183","razaoSocial":"PHARMASCIENCE INDUSTRIA FARMACEUTICA S.A","numeroAutorizacao":"1017173","cnpjFormatado":"25.773.037/0001-83"},"processo":{"numero":"2500000137499","situacao":29,"numeroProcessoFormatado":"25000.001374/99"}},{"ordem":3,"produto":{"codigo":571,"nome":"ALBENDAL","numeroRegistro":"117170017","tipo":{"codigo":1,"descricao":null},"categoria":null,"situacaoRotulo":null,"dataVencimento":null,"mesAnoVencimento":"022010","dataVencimentoRegistro":"2010-02-01T00:00:00.000-0300","principioAtivo":null,"situacaoApresentacao":"Caduco/Cancelado","dataRegistro":"2000-02-24T00:00:00.000-0200","categoriaRegulatoria":{"codigo":8,"descricao":"Similar"},"medicamentoReferencia":null,"categoriaProduto":null,"tipoAutorizacao":"REGISTRADO","numeroRegistroFormatado":"117170017","mesAnoVencimentoFormatado":"02/2010","acancelar":false},"empresa":{"cnpj":"25773037000183","razaoSocial":"PHARMASCIENCE INDUSTRIA FARMACEUTICA S.A","numeroAutorizacao":"1017173","cnpjFormatado":"25.773.037/0001-83"},"processo":{"numero":"2500000138099","situacao":29,"numeroProcessoFormatado":"25000.001380/99"}},{"ordem":4,"produto":{"codigo":413554,"nome":"ALCANATAN","numeroRegistro":"117170058","tipo":{"codigo":1,"descricao":null},"categoria":null,"situacaoRotulo":null,"dataVencimento":null,"mesAnoVencimento":"082025","dataVencimentoRegistro":"2025-08-01T00:00:00.000-0300","principioAtivo":null,"situacaoApresentacao":"Caduco/Cancelado","dataRegistro":"2005-08-15T00:00:00.000-0300","categoriaRegulatoria":{"codigo":4,"descricao":"Fitoterápico"},"medicamentoReferencia":null,"categoriaProduto":null,"tipoAutorizacao":"REGISTRADO","numeroRegistroFormatado":"117170058","mesAnoVencimentoFormatado":"08/2025","acancelar":false},"empresa":{"cnpj":"25773037000183","razaoSocial":"PHARMASCIENCE INDUSTRIA FARMACEUTICA S.A","numeroAutorizacao":"1017173","cnpjFormatado":"25.773.037/0001-83"},"processo":{"numero":"25351138483200588","situacao":29,"numeroProcessoFormatado":"25351.138483/2005-88"}},{"ordem":5,"produto":{"codigo":284490,"nome":"ALERGCORTEM","numeroRegistro":"117170047","tipo":{"codigo":1,"descricao":null},"categoria":null,"situacaoRotulo":null,"dataVencimento":null,"mesAnoVencimento":"092013","dataVencimentoRegistro":"2013-09-01T00:00:00.000-0300","principioAtivo":null,"situacaoApresentacao":"Caduco/Cancelado","dataRegistro":"2003-09-18T00:00:00.000-0300","categoriaRegulatoria":{"codigo":8,"descricao":"Similar"},"medicamentoReferencia":null,"categoriaProduto":null,"tipoAutorizacao":"REGISTRADO","numeroRegistroFormatado":"117170047","mesAnoVencimentoFormatado":"09/2013","acancelar":false},"empresa":{"cnpj":"25773037000183","razaoSocial":"PHARMASCIENCE INDUSTRIA FARMACEUTICA S.A","numeroAutorizacao":"1017173","cnpjFormatado":"25.773.037/0001-83"},"processo":{"numero":"25351024470200361","situacao":20,"numeroProcessoFormatado":"25351.024470/2003-61"}},{"ordem":6,"produto":{"codigo":406713,"nome":"AMISTOFENO","numeroRegistro":"117170059","tipo":{"codigo":1,"descricao":null},"categoria":null,"situacaoRotulo":null,"dataVencimento":null,"mesAnoVencimento":"082010","dataVencimentoRegistro":"2010-08-01T00:00:00.000-0300","principioAtivo":null,"situacaoApresentacao":"Caduco/Cancelado","dataRegistro":"2005-10-03T00:00:00.000-0300","categoriaRegulatoria":{"codigo":8,"descricao":"Similar"},"medicamentoReferencia":null,"categoriaProduto":null,"tipoAutorizacao":"REGISTRADO","numeroRegistroFormatado":"117170059","mesAnoVencimentoFormatado":"08/2010","acancelar":false},"empresa":{"cnpj":"25773037000183","razaoSocial":"PHARMASCIENCE INDUSTRIA FARMACEUTICA S.A","numeroAutorizacao":"1017173","cnpjFormatado":"25.773.037/0001-83"},"processo":{"numero":"25351025826200383","situacao":29,"numeroProcessoFormatado":"25351.025826/2003-83"}},{"ordem":7,"produto":{"codigo":7809,"nome":"ANEMIFER","numeroRegistro":"117170015","tipo":{"codigo":1,"descricao":null},"categoria":null,"situacaoRotulo":null,"dataVencimento":"2025-02-04T00:00:00.000-0300","mesAnoVencimento":"022025","dataVencimentoRegistro":"2025-02-01T00:00:00.000-0300","principioAtivo":"SULFATO FERROSO, SULFATO FERROSO HEPTAIDRATADO","situacaoApresentacao":"Válido","dataRegistro":"2000-02-09T00:00:00.000-0200","categoriaRegulatoria":{"codigo":3,"descricao":"Específico"},"medicamentoReferencia":null,"categoriaProduto":null,"tipoAutorizacao":"REGISTRADO","numeroRegistroFormatado":"117170015","mesAnoVencimentoFormatado":"02/2025","acancelar":false},"empresa":{"cnpj":"25773037000183","razaoSocial":"PHARMASCIENCE INDUSTRIA FARMACEUTICA S.A","numeroAutorizacao":"1017173","cnpjFormatado":"25.773.037/0001-83"},"processo":{"numero":"250000013789910","situacao":29,"numeroProcessoFormatado":"25000.001378/99-10"}},{"ordem":8,"produto":{"codigo":2416,"nome":"APETIVAN BC","numeroRegistro":"117170011","tipo":{"codigo":1,"descricao":null},"categoria":null,"situacaoRotulo":null,"dataVencimento":null,"mesAnoVencimento":"082029","dataVencimentoRegistro":"2029-08-01T00:00:00.000-0300","principioAtivo":"CLORIDRATO DE CIPROEPTADINA, CLORIDRATO DE TIAMINA, VITAMINA B2, VITAMINA B6, NICOTINAMIDA, VITAMINA C","situacaoApresentacao":"Válido","dataRegistro":"1999-08-09T00:00:00.000-0300","categoriaRegulatoria":{"codigo":8,"descricao":"Similar"},"medicamentoReferencia":null,"categoriaProduto":null,"tipoAutorizacao":"REGISTRADO","numeroRegistroFormatado":"117170011","mesAnoVencimentoFormatado":"08/2029","acancelar":false},"empresa":{"cnpj":"25773037000183","razaoSocial":"PHARMASCIENCE INDUSTRIA FARMACEUTICA S.A","numeroAutorizacao":"1017173","cnpjFormatado":"25.773.037/0001-83"},"processo":{"numero":"250000178069808","situacao":29,"numeroProcessoFormatado":"25000.017806/98-08"}},{"ordem":9,"produto":{"codigo":8430,"nome":"ASSETIL","numeroRegistro":"117170028","tipo":{"codigo":1,"descricao":null},"categoria":null,"situacaoRotulo":null,"dataVencimento":null,"mesAnoVencimento":"072010","dataVencimentoRegistro":"2010-07-01T00:00:00.000-0300","principioAtivo":null,"situacaoApresentacao":"Caduco/Cancelado","dataRegistro":"2000-07-20T00:00:00.000-0300","categoriaRegulatoria":{"codigo":8,"descricao":"Similar"},"medicamentoReferencia":null,"categoriaProduto":null,"tipoAutorizacao":"REGISTRADO","numeroRegistroFormatado":"117170028","mesAnoVencimentoFormatado":"07/2010","acancelar":false},"empresa":{"cnpj":"25773037000183","razaoSocial":"PHARMASCIENCE INDUSTRIA FARMACEUTICA S.A","numeroAutorizacao":"1017173","cnpjFormatado":"25.773.037/0001-83"},"processo":{"numero":"250000551799977","situacao":29,"numeroProcessoFormatado":"25000.055179/99-77"}},{"ordem":10,"produto":{"codigo":582117,"nome":"AZITROMICINA","numeroRegistro":"117170070","tipo":{"codigo":1,"descricao":null},"categoria":null,"situacaoRotulo":null,"dataVencimento":null,"mesAnoVencimento":"042029","dataVencimentoRegistro":"2029-04-01T00:00:00.000-0300","principioAtivo":"AZITROMICINA DI-hIDRATADA","situacaoApresentacao":"Válido","dataRegistro":"2009-04-06T00:00:00.000-0300","categoriaRegulatoria":{"codigo":5,"descricao":"Genérico"},"medicamentoReferencia":"ZITROMAX","categoriaProduto":null,"tipoAutorizacao":"REGISTRADO","numeroRegistroFormatado":"117170070","mesAnoVencimentoFormatado":"04/2029","acancelar":false},"empresa":{"cnpj":"25773037000183","razaoSocial":"PHARMASCIENCE INDUSTRIA FARMACEUTICA S.A","numeroAutorizacao":"1017173","cnpjFormatado":"25.773.037/0001-83"},"processo":{"numero":"25351290080200891","situacao":29,"numeroProcessoFormatado":"25351.290080/2008-91"}},{"ordem":11,"produto":{"codigo":595498,"nome":"BABYTOL","numeroRegistro":"117170075","tipo":{"codigo":1,"descricao":null},"categoria":null,"situacaoRotulo":null,"dataVencimento":null,"mesAnoVencimento":"042015","dataVencimentoRegistro":"2015-04-01T00:00:00.000-0300","principioAtivo":null,"situacaoApresentacao":"Caduco/Cancelado","dataRegistro":"2010-04-12T00:00:00.000-0300","categoriaRegulatoria":{"codigo":3,"descricao":"Específico"},"medicamentoReferencia":null,"categoriaProduto":null,"tipoAutorizacao":"REGISTRADO","numeroRegistroFormatado":"117170075","mesAnoVencimentoFormatado":"04/2015","acancelar":false},"empresa":{"cnpj":"25773037000183","razaoSocial":"PHARMASCIENCE INDUSTRIA FARMACEUTICA S.A","numeroAutorizacao":"1017173","cnpjFormatado":"25.773.037/0001-83"},"processo":{"numero":"25351438990200861","situacao":29,"numeroProcessoFormatado":"25351.438990/2008-61"}},{"ordem":12,"produto":{"codigo":1101,"nome":"BENZODERM","numeroRegistro":"117170002","tipo":{"codigo":1,"descricao":null},"categoria":null,"situacaoRotulo":null,"dataVencimento":"2027-10-04T00:00:00.000-0300","mesAnoVencimento":"102027","dataVencimentoRegistro":"2027-10-01T00:00:00.000-0300","principioAtivo":null,"situacaoApresentacao":"Caduco/Cancelado","dataRegistro":"1997-10-06T00:00:00.000-0300","categoriaRegulatoria":{"codigo":8,"descricao":"Similar"},"medicamentoReferencia":null,"categoriaProduto":null,"tipoAutorizacao":"REGISTRADO","numeroRegistroFormatado":"117170002","mesAnoVencimentoFormatado":"10/2027","acancelar":false},"empresa":{"cnpj":"25773037000183","razaoSocial":"PHARMASCIENCE INDUSTRIA FARMACEUTICA S.A","numeroAutorizacao":"1017173","cnpjFormatado":"25.773.037/0001-83"},"processo":{"numero":"250000410049611","situacao":29,"numeroProcessoFormatado":"25000.041004/96-11"}},{"ordem":13,"produto":{"codigo":7297,"nome":"BIOFORTÔNICO","numeroRegistro":"117170040","tipo":{"codigo":1,"descricao":null},"categoria":null,"situacaoRotulo":null,"dataVencimento":null,"mesAnoVencimento":"042006","dataVencimentoRegistro":"2006-04-01T00:00:00.000-0300","principioAtivo":null,"situacaoApresentacao":"Caduco/Cancelado","dataRegistro":"2001-04-11T00:00:00.000-0300","categoriaRegulatoria":{"codigo":8,"descricao":"Similar"},"medicamentoReferencia":null,"categoriaProduto":null,"tipoAutorizacao":"REGISTRADO","numeroRegistroFormatado":"117170040","mesAnoVencimentoFormatado":"04/2006","acancelar":false},"empresa":{"cnpj":"25773037000183","razaoSocial":"PHARMASCIENCE INDUSTRIA FARMACEUTICA S.A","numeroAutorizacao":"1017173","cnpjFormatado":"25.773.037/0001-83"},"processo":{"numero":"250000368769631","situacao":29,"numeroProcessoFormatado":"25000.036876/96-31"}},{"ordem":14,"produto":{"codigo":538629,"nome":"BIOFORTÔNICO","numeroRegistro":"117170067","tipo":{"codigo":1,"descricao":null},"categoria":null,"situacaoRotulo":null,"dataVencimento":null,"mesAnoVencimento":"122027","dataVencimentoRegistro":"2027-12-01T00:00:00.000-0300","principioAtivo":"SULFATO FERROSO HEPTAIDRATADO, CLORIDRATO DE PIRIDOXINA, NICOTINAMIDA","situacaoApresentacao":"Válido","dataRegistro":"2007-12-17T00:00:00.000-0300","categoriaRegulatoria":{"codigo":3,"descricao":"Específico"},"medicamentoReferencia":null,"categoriaProduto":null,"tipoAutorizacao":"REGISTRADO","numeroRegistroFormatado":"117170067","mesAnoVencimentoFormatado":"12/2027","acancelar":false},"empresa":{"cnpj":"25773037000183","razaoSocial":"PHARMASCIENCE INDUSTRIA FARMACEUTICA S.A","numeroAutorizacao":"1017173","cnpjFormatado":"25.773.037/0001-83"},"processo":{"numero":"25351341293200716","situacao":29,"numeroProcessoFormatado":"25351.341293/2007-16"}},{"ordem":15,"produto":{"codigo":6861,"nome":"BIOHEPATON","numeroRegistro":"117170044","tipo":{"codigo":1,"descricao":null},"categoria":null,"situacaoRotulo":null,"dataVencimento":null,"mesAnoVencimento":"082006","dataVencimentoRegistro":"2006-08-01T00:00:00.000-0300","principioAtivo":null,"situacaoApresentacao":"Caduco/Cancelado","dataRegistro":"2001-08-24T00:00:00.000-0300","categoriaRegulatoria":{"codigo":null,"descricao":null},"medicamentoReferencia":null,"categoriaProduto":null,"tipoAutorizacao":"REGISTRADO","numeroRegistroFormatado":"117170044","mesAnoVencimentoFormatado":"08/2006","acancelar":false},"empresa":{"cnpj":"25773037000183","razaoSocial":"PHARMASCIENCE INDUSTRIA FARMACEUTICA S.A","numeroAutorizacao":"1017173","cnpjFormatado":"25.773.037/0001-83"},"processo":{"numero":"253510040780162","situacao":29,"numeroProcessoFormatado":"25351.004078/01-62"}},{"ordem":16,"produto":{"codigo":645737,"nome":"BIOHEPATON","numeroRegistro":"117170074","tipo":{"codigo":1,"descricao":null},"categoria":null,"situacaoRotulo":null,"dataVencimento":null,"mesAnoVencimento":"012030","dataVencimentoRegistro":"2030-01-01T00:00:00.000-0300","principioAtivo":"PEUMUS BOLDUS MOLINA","situacaoApresentacao":"Válido","dataRegistro":"2010-01-25T00:00:00.000-0300","categoriaRegulatoria":{"codigo":4,"descricao":"Fitoterápico"},"medicamentoReferencia":null,"categoriaProduto":null,"tipoAutorizacao":"REGISTRADO","numeroRegistroFormatado":"117170074","mesAnoVencimentoFormatado":"01/2030","acancelar":false},"empresa":{"cnpj":"25773037000183","razaoSocial":"PHARMASCIENCE INDUSTRIA FARMACEUTICA S.A","numeroAutorizacao":"1017173","cnpjFormatado":"25.773.037/0001-83"},"processo":{"numero":"25351176531200978","situacao":29,"numeroProcessoFormatado":"25351.176531/2009-78"}},{"ordem":17,"produto":{"codigo":1792,"nome":"CETACONAL","numeroRegistro":"117170042","tipo":{"codigo":1,"descricao":null},"categoria":null,"situacaoRotulo":null,"dataVencimento":"2011-05-21T00:00:00.000-0300","mesAnoVencimento":"052011","dataVencimentoRegistro":"2011-05-01T00:00:00.000-0300","principioAtivo":null,"situacaoApresentacao":"Caduco/Cancelado","dataRegistro":"2001-05-31T00:00:00.000-0300","categoriaRegulatoria":{"codigo":8,"descricao":"Similar"},"medicamentoReferencia":"NIZORAL","categoriaProduto":null,"tipoAutorizacao":"REGISTRADO","numeroRegistroFormatado":"117170042","mesAnoVencimentoFormatado":"05/2011","acancelar":false},"empresa":{"cnpj":"25773037000183","razaoSocial":"PHARMASCIENCE INDUSTRIA FARMACEUTICA S.A","numeroAutorizacao":"1017173","cnpjFormatado":"25.773.037/0001-83"},"processo":{"numero":"250000008539986","situacao":29,"numeroProcessoFormatado":"25000.000853/99-86"}},{"ordem":18,"produto":{"codigo":520959,"nome":"CISTITRAT","numeroRegistro":"117170066","tipo":{"codigo":1,"descricao":null},"categoria":null,"situacaoRotulo":null,"dataVencimento":null,"mesAnoVencimento":"082012","dataVencimentoRegistro":"2012-08-01T00:00:00.000-0300","principioAtivo":null,"situacaoApresentacao":"Caduco/Cancelado","dataRegistro":"2007-08-13T00:00:00.000-0300","categoriaRegulatoria":{"codigo":4,"descricao":"Fitoterápico"},"medicamentoReferencia":null,"categoriaProduto":null,"tipoAutorizacao":"REGISTRADO","numeroRegistroFormatado":"117170066","mesAnoVencimentoFormatado":"08/2012","acancelar":false},"empresa":{"cnpj":"25773037000183","razaoSocial":"PHARMASCIENCE INDUSTRIA FARMACEUTICA S.A","numeroAutorizacao":"1017173","cnpjFormatado":"25.773.037/0001-83"},"processo":{"numero":"25351015915200745","situacao":29,"numeroProcessoFormatado":"25351.015915/2007-45"}},{"ordem":19,"produto":{"codigo":357996,"nome":"CITROBION C","numeroRegistro":"117170049","tipo":{"codigo":1,"descricao":null},"categoria":null,"situacaoRotulo":null,"dataVencimento":null,"mesAnoVencimento":"032019","dataVencimentoRegistro":"2019-03-01T00:00:00.000-0300","principioAtivo":null,"situacaoApresentacao":"Caduco/Cancelado","dataRegistro":"2004-03-12T00:00:00.000-0300","categoriaRegulatoria":{"codigo":8,"descricao":"Similar"},"medicamentoReferencia":null,"categoriaProduto":null,"tipoAutorizacao":"REGISTRADO","numeroRegistroFormatado":"117170049","mesAnoVencimentoFormatado":"03/2019","acancelar":false},"empresa":{"cnpj":"25773037000183","razaoSocial":"PHARMASCIENCE INDUSTRIA FARMACEUTICA S.A","numeroAutorizacao":"1017173","cnpjFormatado":"25.773.037/0001-83"},"processo":{"numero":"253510080310221","situacao":29,"numeroProcessoFormatado":"25351.008031/02-21"}},{"ordem":20,"produto":{"codigo":3099,"nome":"COMPLEXAN","numeroRegistro":"117170024","tipo":{"codigo":1,"descricao":null},"categoria":null,"situacaoRotulo":null,"dataVencimento":null,"mesAnoVencimento":"052010","dataVencimentoRegistro":"2010-05-01T00:00:00.000-0300","principioAtivo":null,"situacaoApresentacao":"Caduco/Cancelado","dataRegistro":"2000-05-19T00:00:00.000-0300","categoriaRegulatoria":{"codigo":8,"descricao":"Similar"},"medicamentoReferencia":null,"categoriaProduto":null,"tipoAutorizacao":"REGISTRADO","numeroRegistroFormatado":"117170024","mesAnoVencimentoFormatado":"05/2010","acancelar":false},"empresa":{"cnpj":"25773037000183","razaoSocial":"PHARMASCIENCE INDUSTRIA FARMACEUTICA S.A","numeroAutorizacao":"1017173","cnpjFormatado":"25.773.037/0001-83"},"processo":{"numero":"2500000137799","situacao":29,"numeroProcessoFormatado":"25000.001377/99"}},{"ordem":21,"produto":{"codigo":3424,"nome":"DICLOFENACO SODICO","numeroRegistro":"117170043","tipo":{"codigo":1,"descricao":null},"categoria":null,"situacaoRotulo":null,"dataVencimento":null,"mesAnoVencimento":"062011","dataVencimentoRegistro":"2011-06-01T00:00:00.000-0300","principioAtivo":null,"situacaoApresentacao":"Caduco/Cancelado","dataRegistro":"2001-06-06T00:00:00.000-0300","categoriaRegulatoria":{"codigo":8,"descricao":"Similar"},"medicamentoReferencia":null,"categoriaProduto":null,"tipoAutorizacao":"REGISTRADO","numeroRegistroFormatado":"117170043","mesAnoVencimentoFormatado":"06/2011","acancelar":false},"empresa":{"cnpj":"25773037000183","razaoSocial":"PHARMASCIENCE INDUSTRIA FARMACEUTICA S.A","numeroAutorizacao":"1017173","cnpjFormatado":"25.773.037/0001-83"},"processo":{"numero":"250000013759921","situacao":29,"numeroProcessoFormatado":"25000.001375/99-21"}},{"ordem":22,"produto":{"codigo":2016,"nome":"DORTRIRELAX","numeroRegistro":"117170014","tipo":{"codigo":1,"descricao":null},"categoria":null,"situacaoRotulo":null,"dataVencimento":null,"mesAnoVencimento":"112029","dataVencimentoRegistro":"2029-11-01T00:00:00.000-0300","principioAtivo":"CITRATO DE ORFENADRINA, DIPIRONA, CAFEÍNA ANIDRA","situacaoApresentacao":"Válido","dataRegistro":"1999-11-22T00:00:00.000-0200","categoriaRegulatoria":{"codigo":8,"descricao":"Similar"},"medicamentoReferencia":"DORFLEX","categoriaProduto":null,"tipoAutorizacao":"REGISTRADO","numeroRegistroFormatado":"117170014","mesAnoVencimentoFormatado":"11/2029","acancelar":false},"empresa":{"cnpj":"25773037000183","razaoSocial":"PHARMASCIENCE INDUSTRIA FARMACEUTICA S.A","numeroAutorizacao":"1017173","cnpjFormatado":"25.773.037/0001-83"},"processo":{"numero":"250000008529913","situacao":29,"numeroProcessoFormatado":"25000.000852/99-13"}},{"ordem":23,"produto":{"codigo":1350663,"nome":"ENJOY","numeroRegistro":"117170079","tipo":{"codigo":1,"descricao":null},"categoria":null,"situacaoRotulo":null,"dataVencimento":null,"mesAnoVencimento":"092027","dataVencimentoRegistro":"2027-09-01T00:00:00.000-0300","principioAtivo":"HIDROXIDO DE ALUMÍNIO, ACIDO ACETILSALICILICO, MALEATO DE MEPIRAMINA, CAFEÍNA","situacaoApresentacao":"Válido","dataRegistro":"2019-09-23T00:00:00.000-0300","categoriaRegulatoria":{"codigo":8,"descricao":"Similar"},"medicamentoReferencia":"ENGOV","categoriaProduto":null,"tipoAutorizacao":"REGISTRADO","numeroRegistroFormatado":"117170079","mesAnoVencimentoFormatado":"09/2027","acancelar":false},"empresa":{"cnpj":"25773037000183","razaoSocial":"PHARMASCIENCE INDUSTRIA FARMACEUTICA S.A","numeroAutorizacao":"1017173","cnpjFormatado":"25.773.037/0001-83"},"processo":{"numero":"25351452983201925","situacao":29,"numeroProcessoFormatado":"25351.452983/2019-25"}},{"ordem":24,"produto":{"codigo":3569,"nome":"ENTEROFTAL","numeroRegistro":"117170032","tipo":{"codigo":1,"descricao":null},"categoria":null,"situacaoRotulo":null,"dataVencimento":null,"mesAnoVencimento":"072025","dataVencimentoRegistro":"2025-07-01T00:00:00.000-0300","principioAtivo":null,"situacaoApresentacao":"Caduco/Cancelado","dataRegistro":"2000-07-19T00:00:00.000-0300","categoriaRegulatoria":{"codigo":8,"descricao":"Similar"},"medicamentoReferencia":null,"categoriaProduto":null,"tipoAutorizacao":"REGISTRADO","numeroRegistroFormatado":"117170032","mesAnoVencimentoFormatado":"07/2025","acancelar":false},"empresa":{"cnpj":"25773037000183","razaoSocial":"PHARMASCIENCE INDUSTRIA FARMACEUTICA S.A","numeroAutorizacao":"1017173","cnpjFormatado":"25.773.037/0001-83"},"processo":{"numero":"250000551769989","situacao":29,"numeroProcessoFormatado":"25000.055176/99-89"}},{"ordem":25,"produto":{"codigo":510216,"nome":"FINEST EG","numeroRegistro":"117170065","tipo":{"codigo":1,"descricao":null},"categoria":null,"situacaoRotulo":null,"dataVencimento":null,"mesAnoVencimento":"072027","dataVencimentoRegistro":"2027-07-01T00:00:00.000-0300","principioAtivo":"PANAX GINSENG C. A. MEY.","situacaoApresentacao":"Válido","dataRegistro":"2007-07-02T00:00:00.000-0300","categoriaRegulatoria":{"codigo":4,"descricao":"Fitoterápico"},"medicamentoReferencia":null,"categoriaProduto":null,"tipoAutorizacao":"REGISTRADO","numeroRegistroFormatado":"117170065","mesAnoVencimentoFormatado":"07/2027","acancelar":false},"empresa":{"cnpj":"25773037000183","razaoSocial":"PHARMASCIENCE INDUSTRIA FARMACEUTICA S.A","numeroAutorizacao":"1017173","cnpjFormatado":"25.773.037/0001-83"},"processo":{"numero":"25351519472200686","situacao":29,"numeroProcessoFormatado":"25351.519472/2006-86"}},{"ordem":26,"produto":{"codigo":7464,"nome":"FISIOSEPT","numeroRegistro":"117170027","tipo":{"codigo":1,"descricao":null},"categoria":null,"situacaoRotulo":null,"dataVencimento":null,"mesAnoVencimento":"072010","dataVencimentoRegistro":"2010-07-01T00:00:00.000-0300","principioAtivo":null,"situacaoApresentacao":"Caduco/Cancelado","dataRegistro":"2000-07-17T00:00:00.000-0300","categoriaRegulatoria":{"codigo":8,"descricao":"Similar"},"medicamentoReferencia":null,"categoriaProduto":null,"tipoAutorizacao":"REGISTRADO","numeroRegistroFormatado":"117170027","mesAnoVencimentoFormatado":"07/2010","acancelar":false},"empresa":{"cnpj":"25773037000183","razaoSocial":"PHARMASCIENCE INDUSTRIA FARMACEUTICA S.A","numeroAutorizacao":"1017173","cnpjFormatado":"25.773.037/0001-83"},"processo":{"numero":"250000008549949","situacao":29,"numeroProcessoFormatado":"25000.000854/99-49"}},{"ordem":27,"produto":{"codigo":4251,"nome":"FLUCONAN","numeroRegistro":"117170034","tipo":{"codigo":1,"descricao":null},"categoria":null,"situacaoRotulo":null,"dataVencimento":null,"mesAnoVencimento":"092010","dataVencimentoRegistro":"2010-09-01T00:00:00.000-0300","principioAtivo":null,"situacaoApresentacao":"Caduco/Cancelado","dataRegistro":"2000-09-20T00:00:00.000-0300","categoriaRegulatoria":{"codigo":8,"descricao":"Similar"},"medicamentoReferencia":null,"categoriaProduto":null,"tipoAutorizacao":"REGISTRADO","numeroRegistroFormatado":"117170034","mesAnoVencimentoFormatado":"09/2010","acancelar":false},"empresa":{"cnpj":"25773037000183","razaoSocial":"PHARMASCIENCE INDUSTRIA FARMACEUTICA S.A","numeroAutorizacao":"1017173","cnpjFormatado":"25.773.037/0001-83"},"processo":{"numero":"250000552139911","situacao":29,"numeroProcessoFormatado":"25000.055213/99-11"}},{"ordem":28,"produto":{"codigo":7824,"nome":"FORTÔNICO","numeroRegistro":"117170035","tipo":{"codigo":1,"descricao":null},"categoria":null,"situacaoRotulo":null,"dataVencimento":null,"mesAnoVencimento":"102005","dataVencimentoRegistro":"2005-10-01T00:00:00.000-0300","principioAtivo":null,"situacaoApresentacao":"Caduco/Cancelado","dataRegistro":"2000-10-19T00:00:00.000-0300","categoriaRegulatoria":{"codigo":8,"descricao":"Similar"},"medicamentoReferencia":null,"categoriaProduto":null,"tipoAutorizacao":"REGISTRADO","numeroRegistroFormatado":"117170035","mesAnoVencimentoFormatado":"10/2005","acancelar":false},"empresa":{"cnpj":"25773037000183","razaoSocial":"PHARMASCIENCE INDUSTRIA FARMACEUTICA S.A","numeroAutorizacao":"1017173","cnpjFormatado":"25.773.037/0001-83"},"processo":{"numero":"250000551899921","situacao":29,"numeroProcessoFormatado":"25000.055189/99-21"}},{"ordem":29,"produto":{"codigo":546532,"nome":"FORTÔNICO","numeroRegistro":"117170069","tipo":{"codigo":1,"descricao":null},"categoria":null,"situacaoRotulo":null,"dataVencimento":null,"mesAnoVencimento":"032013","dataVencimentoRegistro":"2013-03-01T00:00:00.000-0300","principioAtivo":null,"situacaoApresentacao":"Caduco/Cancelado","dataRegistro":"2008-03-17T00:00:00.000-0300","categoriaRegulatoria":{"codigo":3,"descricao":"Específico"},"medicamentoReferencia":null,"categoriaProduto":null,"tipoAutorizacao":"REGISTRADO","numeroRegistroFormatado":"117170069","mesAnoVencimentoFormatado":"03/2013","acancelar":false},"empresa":{"cnpj":"25773037000183","razaoSocial":"PHARMASCIENCE INDUSTRIA FARMACEUTICA S.A","numeroAutorizacao":"1017173","cnpjFormatado":"25.773.037/0001-83"},"processo":{"numero":"25351467977200739","situacao":29,"numeroProcessoFormatado":"25351.467977/2007-39"}},{"ordem":30,"produto":{"codigo":1361548,"nome":"FOSMORYL","numeroRegistro":"117170083","tipo":{"codigo":1,"descricao":null},"categoria":null,"situacaoRotulo":null,"dataVencimento":null,"mesAnoVencimento":"082031","dataVencimentoRegistro":"2031-08-01T00:00:00.000-0300","principioAtivo":"FOSFOMICINA TROMETAMOL","situacaoApresentacao":"Válido","dataRegistro":"2021-08-30T00:00:00.000-0300","categoriaRegulatoria":{"codigo":8,"descricao":"Similar"},"medicamentoReferencia":"MONURIL","categoriaProduto":null,"tipoAutorizacao":"REGISTRADO","numeroRegistroFormatado":"117170083","mesAnoVencimentoFormatado":"08/2031","acancelar":false},"empresa":{"cnpj":"25773037000183","razaoSocial":"PHARMASCIENCE INDUSTRIA FARMACEUTICA S.A","numeroAutorizacao":"1017173","cnpjFormatado":"25.773.037/0001-83"},"processo":{"numero":"25351600307201974","situacao":29,"numeroProcessoFormatado":"25351.600307/2019-74"}},{"ordem":31,"produto":{"codigo":4461,"nome":"FUROSEMIL","numeroRegistro":"117170025","tipo":{"codigo":1,"descricao":null},"categoria":null,"situacaoRotulo":null,"dataVencimento":null,"mesAnoVencimento":"052015","dataVencimentoRegistro":"2015-05-01T00:00:00.000-0300","principioAtivo":null,"situacaoApresentacao":"Caduco/Cancelado","dataRegistro":"2000-05-19T00:00:00.000-0300","categoriaRegulatoria":{"codigo":8,"descricao":"Similar"},"medicamentoReferencia":null,"categoriaProduto":null,"tipoAutorizacao":"REGISTRADO","numeroRegistroFormatado":"117170025","mesAnoVencimentoFormatado":"05/2015","acancelar":false},"empresa":{"cnpj":"25773037000183","razaoSocial":"PHARMASCIENCE INDUSTRIA FARMACEUTICA S.A","numeroAutorizacao":"1017173","cnpjFormatado":"25.773.037/0001-83"},"processo":{"numero":"250000013769994","situacao":29,"numeroProcessoFormatado":"25000.001376/99-94"}},{"ordem":32,"produto":{"codigo":4865,"nome":"GASTROFTAL","numeroRegistro":"117170021","tipo":{"codigo":1,"descricao":null},"categoria":null,"situacaoRotulo":null,"dataVencimento":null,"mesAnoVencimento":"042025","dataVencimentoRegistro":"2025-04-01T00:00:00.000-0300","principioAtivo":"HIDROXIDO DE ALUMÍNIO, HIDRÓXIDO DE ALUMÍNIO, HIDRÓXIDO DE MAGNÉSIO, CARBONATO DE CÁLCIO","situacaoApresentacao":"Válido","dataRegistro":"2000-02-24T00:00:00.000-0200","categoriaRegulatoria":{"codigo":3,"descricao":"Específico"},"medicamentoReferencia":null,"categoriaProduto":null,"tipoAutorizacao":"REGISTRADO","numeroRegistroFormatado":"117170021","mesAnoVencimentoFormatado":"04/2025","acancelar":false},"empresa":{"cnpj":"25773037000183","razaoSocial":"PHARMASCIENCE INDUSTRIA FARMACEUTICA S.A","numeroAutorizacao":"1017173","cnpjFormatado":"25.773.037/0001-83"},"processo":{"numero":"250000008519951","situacao":29,"numeroProcessoFormatado":"25000.000851/99-51"}},{"ordem":33,"produto":{"codigo":422904,"nome":"GASTRONAN","numeroRegistro":"117170061","tipo":{"codigo":1,"descricao":null},"categoria":null,"situacaoRotulo":null,"dataVencimento":null,"mesAnoVencimento":"112025","dataVencimentoRegistro":"2025-11-01T00:00:00.000-0300","principioAtivo":null,"situacaoApresentacao":"Caduco/Cancelado","dataRegistro":"2005-11-28T00:00:00.000-0300","categoriaRegulatoria":{"codigo":4,"descricao":"Fitoterápico"},"medicamentoReferencia":null,"categoriaProduto":null,"tipoAutorizacao":"REGISTRADO","numeroRegistroFormatado":"117170061","mesAnoVencimentoFormatado":"11/2025","acancelar":false},"empresa":{"cnpj":"25773037000183","razaoSocial":"PHARMASCIENCE INDUSTRIA FARMACEUTICA S.A","numeroAutorizacao":"1017173","cnpjFormatado":"25.773.037/0001-83"},"processo":{"numero":"25351324573200590","situacao":29,"numeroProcessoFormatado":"25351.324573/2005-90"}},{"ordem":34,"produto":{"codigo":4861,"nome":"GASTROPEPT","numeroRegistro":"117170023","tipo":{"codigo":1,"descricao":null},"categoria":null,"situacaoRotulo":null,"dataVencimento":null,"mesAnoVencimento":"122011","dataVencimentoRegistro":"2011-12-01T00:00:00.000-0300","principioAtivo":null,"situacaoApresentacao":"Caduco/Cancelado","dataRegistro":"2000-04-06T00:00:00.000-0300","categoriaRegulatoria":{"codigo":8,"descricao":"Similar"},"medicamentoReferencia":null,"categoriaProduto":null,"tipoAutorizacao":"REGISTRADO","numeroRegistroFormatado":"117170023","mesAnoVencimentoFormatado":"12/2011","acancelar":false},"empresa":{"cnpj":"25773037000183","razaoSocial":"PHARMASCIENCE INDUSTRIA FARMACEUTICA S.A","numeroAutorizacao":"1017173","cnpjFormatado":"25.773.037/0001-83"},"processo":{"numero":"250000013699929","situacao":29,"numeroProcessoFormatado":"25000.001369/99-29"}},{"ordem":35,"produto":{"codigo":284470,"nome":"GLYCELAX","numeroRegistro":"117170048","tipo":{"codigo":1,"descricao":null},"categoria":null,"situacaoRotulo":null,"dataVencimento":null,"mesAnoVencimento":"092008","dataVencimentoRegistro":"2008-09-01T00:00:00.000-0300","principioAtivo":null,"situacaoApresentacao":"Caduco/Cancelado","dataRegistro":"2003-09-25T00:00:00.000-0300","categoriaRegulatoria":{"codigo":8,"descricao":"Similar"},"medicamentoReferencia":null,"categoriaProduto":null,"tipoAutorizacao":"REGISTRADO","numeroRegistroFormatado":"117170048","mesAnoVencimentoFormatado":"09/2008","acancelar":false},"empresa":{"cnpj":"25773037000183","razaoSocial":"PHARMASCIENCE INDUSTRIA FARMACEUTICA S.A","numeroAutorizacao":"1017173","cnpjFormatado":"25.773.037/0001-83"},"processo":{"numero":"25351024481200341","situacao":29,"numeroProcessoFormatado":"25351.024481/2003-41"}},{"ordem":36,"produto":{"codigo":411855,"nome":"GUACONAT","numeroRegistro":"117170057","tipo":{"codigo":1,"descricao":null},"categoria":null,"situacaoRotulo":null,"dataVencimento":"2025-08-22T00:00:00.000-0300","mesAnoVencimento":"082025","dataVencimentoRegistro":"2025-08-01T00:00:00.000-0300","principioAtivo":"MIKANIA GLOMERATA SPRENG.","situacaoApresentacao":"Válido","dataRegistro":"2005-08-15T00:00:00.000-0300","categoriaRegulatoria":{"codigo":4,"descricao":"Fitoterápico"},"medicamentoReferencia":null,"categoriaProduto":null,"tipoAutorizacao":"REGISTRADO","numeroRegistroFormatado":"117170057","mesAnoVencimentoFormatado":"08/2025","acancelar":false},"empresa":{"cnpj":"25773037000183","razaoSocial":"PHARMASCIENCE INDUSTRIA FARMACEUTICA S.A","numeroAutorizacao":"1017173","cnpjFormatado":"25.773.037/0001-83"},"processo":{"numero":"25351130193200596","situacao":29,"numeroProcessoFormatado":"25351.130193/2005-96"}},{"ordem":37,"produto":{"codigo":409620,"nome":"GUANAT","numeroRegistro":"117170054","tipo":{"codigo":1,"descricao":null},"categoria":null,"situacaoRotulo":null,"dataVencimento":null,"mesAnoVencimento":"062010","dataVencimentoRegistro":"2010-06-01T00:00:00.000-0300","principioAtivo":null,"situacaoApresentacao":"Caduco/Cancelado","dataRegistro":"2005-06-20T00:00:00.000-0300","categoriaRegulatoria":{"codigo":4,"descricao":"Fitoterápico"},"medicamentoReferencia":null,"categoriaProduto":null,"tipoAutorizacao":"REGISTRADO","numeroRegistroFormatado":"117170054","mesAnoVencimentoFormatado":"06/2010","acancelar":false},"empresa":{"cnpj":"25773037000183","razaoSocial":"PHARMASCIENCE INDUSTRIA FARMACEUTICA S.A","numeroAutorizacao":"1017173","cnpjFormatado":"25.773.037/0001-83"},"processo":{"numero":"25351133483200591","situacao":29,"numeroProcessoFormatado":"25351.133483/2005-91"}},{"ordem":38,"produto":{"codigo":541188,"nome":"GUANAT","numeroRegistro":"117170068","tipo":{"codigo":1,"descricao":null},"categoria":null,"situacaoRotulo":null,"dataVencimento":null,"mesAnoVencimento":"022013","dataVencimentoRegistro":"2013-02-01T00:00:00.000-0300","principioAtivo":null,"situacaoApresentacao":"Caduco/Cancelado","dataRegistro":"2008-02-06T00:00:00.000-0300","categoriaRegulatoria":{"codigo":4,"descricao":"Fitoterápico"},"medicamentoReferencia":null,"categoriaProduto":null,"tipoAutorizacao":"REGISTRADO","numeroRegistroFormatado":"117170068","mesAnoVencimentoFormatado":"02/2013","acancelar":false},"empresa":{"cnpj":"25773037000183","razaoSocial":"PHARMASCIENCE INDUSTRIA FARMACEUTICA S.A","numeroAutorizacao":"1017173","cnpjFormatado":"25.773.037/0001-83"},"processo":{"numero":"25351390972200719","situacao":29,"numeroProcessoFormatado":"25351.390972/2007-19"}},{"ordem":39,"produto":{"codigo":407781,"nome":"Ginkgomenil","numeroRegistro":"117170051","tipo":{"codigo":1,"descricao":null},"categoria":null,"situacaoRotulo":null,"dataVencimento":null,"mesAnoVencimento":"042010","dataVencimentoRegistro":"2010-04-01T00:00:00.000-0300","principioAtivo":null,"situacaoApresentacao":"Caduco/Cancelado","dataRegistro":"2005-04-28T00:00:00.000-0300","categoriaRegulatoria":{"codigo":4,"descricao":"Fitoterápico"},"medicamentoReferencia":null,"categoriaProduto":null,"tipoAutorizacao":"REGISTRADO","numeroRegistroFormatado":"117170051","mesAnoVencimentoFormatado":"04/2010","acancelar":false},"empresa":{"cnpj":"25773037000183","razaoSocial":"PHARMASCIENCE INDUSTRIA FARMACEUTICA S.A","numeroAutorizacao":"1017173","cnpjFormatado":"25.773.037/0001-83"},"processo":{"numero":"25351010492200513","situacao":29,"numeroProcessoFormatado":"25351.010492/2005-13"}},{"ordem":40,"produto":{"codigo":4837,"nome":"HIDROXIDO DE MAGNESIO","numeroRegistro":"117170008","tipo":{"codigo":1,"descricao":null},"categoria":null,"situacaoRotulo":null,"dataVencimento":null,"mesAnoVencimento":"052009","dataVencimentoRegistro":"2009-05-01T00:00:00.000-0300","principioAtivo":null,"situacaoApresentacao":"Caduco/Cancelado","dataRegistro":"1999-05-17T00:00:00.000-0300","categoriaRegulatoria":{"codigo":8,"descricao":"Similar"},"medicamentoReferencia":null,"categoriaProduto":null,"tipoAutorizacao":"REGISTRADO","numeroRegistroFormatado":"117170008","mesAnoVencimentoFormatado":"05/2009","acancelar":false},"empresa":{"cnpj":"25773037000183","razaoSocial":"PHARMASCIENCE INDUSTRIA FARMACEUTICA S.A","numeroAutorizacao":"1017173","cnpjFormatado":"25.773.037/0001-83"},"processo":{"numero":"250000181789824","situacao":29,"numeroProcessoFormatado":"25000.018178/98-24"}},{"ordem":41,"produto":{"codigo":4860,"nome":"HIDRÓXIDO DE ALUMÍNIO","numeroRegistro":"117170022","tipo":{"codigo":1,"descricao":null},"categoria":null,"situacaoRotulo":null,"dataVencimento":null,"mesAnoVencimento":"042005","dataVencimentoRegistro":"2005-04-01T00:00:00.000-0300","principioAtivo":null,"situacaoApresentacao":"Caduco/Cancelado","dataRegistro":"2000-02-25T00:00:00.000-0200","categoriaRegulatoria":{"codigo":8,"descricao":"Similar"},"medicamentoReferencia":null,"categoriaProduto":null,"tipoAutorizacao":"REGISTRADO","numeroRegistroFormatado":"117170022","mesAnoVencimentoFormatado":"04/2005","acancelar":false},"empresa":{"cnpj":"25773037000183","razaoSocial":"PHARMASCIENCE INDUSTRIA FARMACEUTICA S.A","numeroAutorizacao":"1017173","cnpjFormatado":"25.773.037/0001-83"},"processo":{"numero":"2500000136999","situacao":29,"numeroProcessoFormatado":"25000.001369/99"}},{"ordem":42,"produto":{"codigo":414767,"nome":"HYPERINAT","numeroRegistro":"117170055","tipo":{"codigo":1,"descricao":null},"categoria":null,"situacaoRotulo":null,"dataVencimento":null,"mesAnoVencimento":"072025","dataVencimentoRegistro":"2025-07-01T00:00:00.000-0300","principioAtivo":"HYPERICUM PERFORATUM L.","situacaoApresentacao":"Válido","dataRegistro":"2005-07-18T00:00:00.000-0300","categoriaRegulatoria":{"codigo":4,"descricao":"Fitoterápico"},"medicamentoReferencia":null,"categoriaProduto":null,"tipoAutorizacao":"REGISTRADO","numeroRegistroFormatado":"117170055","mesAnoVencimentoFormatado":"07/2025","acancelar":false},"empresa":{"cnpj":"25773037000183","razaoSocial":"PHARMASCIENCE INDUSTRIA FARMACEUTICA S.A","numeroAutorizacao":"1017173","cnpjFormatado":"25.773.037/0001-83"},"processo":{"numero":"25351220912200560","situacao":29,"numeroProcessoFormatado":"25351.220912/2005-60"}},{"ordem":43,"produto":{"codigo":369589,"nome":"KALYPTOSAN","numeroRegistro":"117170050","tipo":{"codigo":1,"descricao":null},"categoria":null,"situacaoRotulo":null,"dataVencimento":null,"mesAnoVencimento":"102009","dataVencimentoRegistro":"2009-10-01T00:00:00.000-0300","principioAtivo":null,"situacaoApresentacao":"Caduco/Cancelado","dataRegistro":"2004-10-04T00:00:00.000-0300","categoriaRegulatoria":{"codigo":4,"descricao":"Fitoterápico"},"medicamentoReferencia":null,"categoriaProduto":null,"tipoAutorizacao":"REGISTRADO","numeroRegistroFormatado":"117170050","mesAnoVencimentoFormatado":"10/2009","acancelar":false},"empresa":{"cnpj":"25773037000183","razaoSocial":"PHARMASCIENCE INDUSTRIA FARMACEUTICA S.A","numeroAutorizacao":"1017173","cnpjFormatado":"25.773.037/0001-83"},"processo":{"numero":"25351016922200411","situacao":29,"numeroProcessoFormatado":"25351.016922/2004-11"}},{"ordem":44,"produto":{"codigo":2678,"nome":"KAOSEC","numeroRegistro":"117170026","tipo":{"codigo":1,"descricao":null},"categoria":null,"situacaoRotulo":null,"dataVencimento":null,"mesAnoVencimento":"072025","dataVencimentoRegistro":"2025-07-01T00:00:00.000-0300","principioAtivo":"CLORIDRATO DE LOPERAMIDA","situacaoApresentacao":"Válido","dataRegistro":"2000-07-17T00:00:00.000-0300","categoriaRegulatoria":{"codigo":8,"descricao":"Similar"},"medicamentoReferencia":"IMOSEC","categoriaProduto":null,"tipoAutorizacao":"REGISTRADO","numeroRegistroFormatado":"117170026","mesAnoVencimentoFormatado":"07/2025","acancelar":false},"empresa":{"cnpj":"25773037000183","razaoSocial":"PHARMASCIENCE INDUSTRIA FARMACEUTICA S.A","numeroAutorizacao":"1017173","cnpjFormatado":"25.773.037/0001-83"},"processo":{"numero":"250000551729928","situacao":29,"numeroProcessoFormatado":"25000.055172/99-28"}},{"ordem":45,"produto":{"codigo":5642,"nome":"MEBENDAL","numeroRegistro":"117170001","tipo":{"codigo":1,"descricao":null},"categoria":null,"situacaoRotulo":null,"dataVencimento":null,"mesAnoVencimento":"102012","dataVencimentoRegistro":"2012-10-01T00:00:00.000-0300","principioAtivo":null,"situacaoApresentacao":"Caduco/Cancelado","dataRegistro":"1997-10-06T00:00:00.000-0300","categoriaRegulatoria":{"codigo":8,"descricao":"Similar"},"medicamentoReferencia":null,"categoriaProduto":null,"tipoAutorizacao":"REGISTRADO","numeroRegistroFormatado":"117170001","mesAnoVencimentoFormatado":"10/2012","acancelar":false},"empresa":{"cnpj":"25773037000183","razaoSocial":"PHARMASCIENCE INDUSTRIA FARMACEUTICA S.A","numeroAutorizacao":"1017173","cnpjFormatado":"25.773.037/0001-83"},"processo":{"numero":"250000409949671","situacao":29,"numeroProcessoFormatado":"25000.040994/96-71"}},{"ordem":46,"produto":{"codigo":5921,"nome":"METRONIDAN","numeroRegistro":"117170013","tipo":{"codigo":1,"descricao":null},"categoria":null,"situacaoRotulo":null,"dataVencimento":null,"mesAnoVencimento":"102009","dataVencimentoRegistro":"2009-10-01T00:00:00.000-0300","principioAtivo":null,"situacaoApresentacao":"Caduco/Cancelado","dataRegistro":"1999-10-11T00:00:00.000-0200","categoriaRegulatoria":{"codigo":8,"descricao":"Similar"},"medicamentoReferencia":null,"categoriaProduto":null,"tipoAutorizacao":"REGISTRADO","numeroRegistroFormatado":"117170013","mesAnoVencimentoFormatado":"10/2009","acancelar":false},"empresa":{"cnpj":"25773037000183","razaoSocial":"PHARMASCIENCE INDUSTRIA FARMACEUTICA S.A","numeroAutorizacao":"1017173","cnpjFormatado":"25.773.037/0001-83"},"processo":{"numero":"250000013729933","situacao":29,"numeroProcessoFormatado":"25000.001372/99-33"}},{"ordem":47,"produto":{"codigo":6253,"nome":"MICONIL","numeroRegistro":"117170041","tipo":{"codigo":1,"descricao":null},"categoria":null,"situacaoRotulo":null,"dataVencimento":"2026-06-04T00:00:00.000-0300","mesAnoVencimento":"062026","dataVencimentoRegistro":"2026-06-01T00:00:00.000-0300","principioAtivo":null,"situacaoApresentacao":"Caduco/Cancelado","dataRegistro":"2001-06-04T00:00:00.000-0300","categoriaRegulatoria":{"codigo":8,"descricao":"Similar"},"medicamentoReferencia":null,"categoriaProduto":null,"tipoAutorizacao":"REGISTRADO","numeroRegistroFormatado":"117170041","mesAnoVencimentoFormatado":"06/2026","acancelar":false},"empresa":{"cnpj":"25773037000183","razaoSocial":"PHARMASCIENCE INDUSTRIA FARMACEUTICA S.A","numeroAutorizacao":"1017173","cnpjFormatado":"25.773.037/0001-83"},"processo":{"numero":"2500000138199","situacao":29,"numeroProcessoFormatado":"25000.001381/99"}},{"ordem":48,"produto":{"codigo":5711,"nome":"NASORUB","numeroRegistro":"117170036","tipo":{"codigo":1,"descricao":null},"categoria":null,"situacaoRotulo":null,"dataVencimento":null,"mesAnoVencimento":"102005","dataVencimentoRegistro":"2005-10-01T00:00:00.000-0300","principioAtivo":null,"situacaoApresentacao":"Caduco/Cancelado","dataRegistro":"2000-10-25T00:00:00.000-0300","categoriaRegulatoria":{"codigo":8,"descricao":"Similar"},"medicamentoReferencia":null,"categoriaProduto":null,"tipoAutorizacao":"REGISTRADO","numeroRegistroFormatado":"117170036","mesAnoVencimentoFormatado":"10/2005","acancelar":false},"empresa":{"cnpj":"25773037000183","razaoSocial":"PHARMASCIENCE INDUSTRIA FARMACEUTICA S.A","numeroAutorizacao":"1017173","cnpjFormatado":"25.773.037/0001-83"},"processo":{"numero":"253510113840038","situacao":29,"numeroProcessoFormatado":"25351.011384/00-38"}},{"ordem":49,"produto":{"codigo":6015,"nome":"NEOSALDOR","numeroRegistro":"117170020","tipo":{"codigo":1,"descricao":null},"categoria":null,"situacaoRotulo":null,"dataVencimento":null,"mesAnoVencimento":"022015","dataVencimentoRegistro":"2015-02-01T00:00:00.000-0300","principioAtivo":null,"situacaoApresentacao":"Caduco/Cancelado","dataRegistro":"2000-02-24T00:00:00.000-0200","categoriaRegulatoria":{"codigo":8,"descricao":"Similar"},"medicamentoReferencia":null,"categoriaProduto":null,"tipoAutorizacao":"REGISTRADO","numeroRegistroFormatado":"117170020","mesAnoVencimentoFormatado":"02/2015","acancelar":false},"empresa":{"cnpj":"25773037000183","razaoSocial":"PHARMASCIENCE INDUSTRIA FARMACEUTICA S.A","numeroAutorizacao":"1017173","cnpjFormatado":"25.773.037/0001-83"},"processo":{"numero":"250000013829997","situacao":29,"numeroProcessoFormatado":"25000.001382/99-97"}},{"ordem":50,"produto":{"codigo":3659,"nome":"NEVRALDOR","numeroRegistro":"117170007","tipo":{"codigo":1,"descricao":null},"categoria":null,"situacaoRotulo":null,"dataVencimento":null,"mesAnoVencimento":"022013","dataVencimentoRegistro":"2013-02-01T00:00:00.000-0300","principioAtivo":null,"situacaoApresentacao":"Caduco/Cancelado","dataRegistro":"1998-02-13T00:00:00.000-0300","categoriaRegulatoria":{"codigo":8,"descricao":"Similar"},"medicamentoReferencia":null,"categoriaProduto":null,"tipoAutorizacao":"REGISTRADO","numeroRegistroFormatado":"117170007","mesAnoVencimentoFormatado":"02/2013","acancelar":false},"empresa":{"cnpj":"25773037000183","razaoSocial":"PHARMASCIENCE INDUSTRIA FARMACEUTICA S.A","numeroAutorizacao":"1017173","cnpjFormatado":"25.773.037/0001-83"},"processo":{"numero":"250000368759678","situacao":29,"numeroProcessoFormatado":"25000.036875/96-78"}},{"ordem":51,"produto":{"codigo":604660,"nome":"NORFLOXACINO","numeroRegistro":"117170073","tipo":{"codigo":1,"descricao":null},"categoria":null,"situacaoRotulo":null,"dataVencimento":null,"mesAnoVencimento":"102029","dataVencimentoRegistro":"2029-10-01T00:00:00.000-0300","principioAtivo":"NORFLOXACINO","situacaoApresentacao":"Válido","dataRegistro":"2009-10-19T00:00:00.000-0300","categoriaRegulatoria":{"codigo":5,"descricao":"Genérico"},"medicamentoReferencia":"FLOXACIN","categoriaProduto":null,"tipoAutorizacao":"REGISTRADO","numeroRegistroFormatado":"117170073","mesAnoVencimentoFormatado":"10/2029","acancelar":false},"empresa":{"cnpj":"25773037000183","razaoSocial":"PHARMASCIENCE INDUSTRIA FARMACEUTICA S.A","numeroAutorizacao":"1017173","cnpjFormatado":"25.773.037/0001-83"},"processo":{"numero":"25351470005200811","situacao":29,"numeroProcessoFormatado":"25351.470005/2008-11"}},{"ordem":52,"produto":{"codigo":6344,"nome":"NORFLOXIN","numeroRegistro":"117170018","tipo":{"codigo":1,"descricao":null},"categoria":null,"situacaoRotulo":null,"dataVencimento":null,"mesAnoVencimento":"022005","dataVencimentoRegistro":"2005-02-01T00:00:00.000-0300","principioAtivo":null,"situacaoApresentacao":"Caduco/Cancelado","dataRegistro":"2000-02-24T00:00:00.000-0200","categoriaRegulatoria":{"codigo":8,"descricao":"Similar"},"medicamentoReferencia":null,"categoriaProduto":null,"tipoAutorizacao":"REGISTRADO","numeroRegistroFormatado":"117170018","mesAnoVencimentoFormatado":"02/2005","acancelar":false},"empresa":{"cnpj":"25773037000183","razaoSocial":"PHARMASCIENCE INDUSTRIA FARMACEUTICA S.A","numeroAutorizacao":"1017173","cnpjFormatado":"25.773.037/0001-83"},"processo":{"numero":"2500000138799","situacao":29,"numeroProcessoFormatado":"25000.001387/99"}},{"ordem":53,"produto":{"codigo":604962,"nome":"NORFLOXINOX","numeroRegistro":"117170072","tipo":{"codigo":1,"descricao":null},"categoria":null,"situacaoRotulo":null,"dataVencimento":null,"mesAnoVencimento":"102014","dataVencimentoRegistro":"2014-10-01T00:00:00.000-0300","principioAtivo":null,"situacaoApresentacao":"Caduco/Cancelado","dataRegistro":"2009-10-19T00:00:00.000-0300","categoriaRegulatoria":{"codigo":8,"descricao":"Similar"},"medicamentoReferencia":null,"categoriaProduto":null,"tipoAutorizacao":"REGISTRADO","numeroRegistroFormatado":"117170072","mesAnoVencimentoFormatado":"10/2014","acancelar":false},"empresa":{"cnpj":"25773037000183","razaoSocial":"PHARMASCIENCE INDUSTRIA FARMACEUTICA S.A","numeroAutorizacao":"1017173","cnpjFormatado":"25.773.037/0001-83"},"processo":{"numero":"25351671818200818","situacao":29,"numeroProcessoFormatado":"25351.671818/2008-18"}},{"ordem":54,"produto":{"codigo":6569,"nome":"PANAX GINSENG C. A. MEY","numeroRegistro":"117170045","tipo":{"codigo":1,"descricao":null},"categoria":null,"situacaoRotulo":null,"dataVencimento":null,"mesAnoVencimento":"112006","dataVencimentoRegistro":"2006-11-01T00:00:00.000-0300","principioAtivo":null,"situacaoApresentacao":"Caduco/Cancelado","dataRegistro":"2001-12-10T00:00:00.000-0200","categoriaRegulatoria":{"codigo":4,"descricao":"Fitoterápico"},"medicamentoReferencia":null,"categoriaProduto":null,"tipoAutorizacao":"REGISTRADO","numeroRegistroFormatado":"117170045","mesAnoVencimentoFormatado":"11/2006","acancelar":false},"empresa":{"cnpj":"25773037000183","razaoSocial":"PHARMASCIENCE INDUSTRIA FARMACEUTICA S.A","numeroAutorizacao":"1017173","cnpjFormatado":"25.773.037/0001-83"},"processo":{"numero":"250000213959819","situacao":29,"numeroProcessoFormatado":"25000.021395/98-19"}},{"ordem":55,"produto":{"codigo":6823,"nome":"PERMETRINA","numeroRegistro":"117170005","tipo":{"codigo":1,"descricao":null},"categoria":null,"situacaoRotulo":null,"dataVencimento":null,"mesAnoVencimento":"012003","dataVencimentoRegistro":"2003-01-01T00:00:00.000-0300","principioAtivo":null,"situacaoApresentacao":"Caduco/Cancelado","dataRegistro":"1998-01-12T00:00:00.000-0300","categoriaRegulatoria":{"codigo":8,"descricao":"Similar"},"medicamentoReferencia":null,"categoriaProduto":null,"tipoAutorizacao":"REGISTRADO","numeroRegistroFormatado":"117170005","mesAnoVencimentoFormatado":"01/2003","acancelar":false},"empresa":{"cnpj":"25773037000183","razaoSocial":"PHARMASCIENCE INDUSTRIA FARMACEUTICA S.A","numeroAutorizacao":"1017173","cnpjFormatado":"25.773.037/0001-83"},"processo":{"numero":"250000410119678","situacao":29,"numeroProcessoFormatado":"25000.041011/96-78"}},{"ordem":56,"produto":{"codigo":2258,"nome":"POLYDRAT","numeroRegistro":"117170019","tipo":{"codigo":1,"descricao":null},"categoria":null,"situacaoRotulo":null,"dataVencimento":null,"mesAnoVencimento":"022019","dataVencimentoRegistro":"2019-02-01T00:00:00.000-0300","principioAtivo":null,"situacaoApresentacao":"Caduco/Cancelado","dataRegistro":"2000-02-24T00:00:00.000-0200","categoriaRegulatoria":{"codigo":8,"descricao":"Similar"},"medicamentoReferencia":null,"categoriaProduto":null,"tipoAutorizacao":"REGISTRADO","numeroRegistroFormatado":"117170019","mesAnoVencimentoFormatado":"02/2019","acancelar":false},"empresa":{"cnpj":"25773037000183","razaoSocial":"PHARMASCIENCE INDUSTRIA FARMACEUTICA S.A","numeroAutorizacao":"1017173","cnpjFormatado":"25.773.037/0001-83"},"processo":{"numero":"250000008459958","situacao":29,"numeroProcessoFormatado":"25000.000845/99-58"}},{"ordem":57,"produto":{"codigo":1266325,"nome":"PRASILENCE","numeroRegistro":"117170078","tipo":{"codigo":1,"descricao":null},"categoria":null,"situacaoRotulo":null,"dataVencimento":null,"mesAnoVencimento":"052029","dataVencimentoRegistro":"2029-05-01T00:00:00.000-0300","principioAtivo":"Passiflora incarnata L.","situacaoApresentacao":"Válido","dataRegistro":"2019-05-06T00:00:00.000-0300","categoriaRegulatoria":{"codigo":4,"descricao":"Fitoterápico"},"medicamentoReferencia":null,"categoriaProduto":null,"tipoAutorizacao":"REGISTRADO","numeroRegistroFormatado":"117170078","mesAnoVencimentoFormatado":"05/2029","acancelar":false},"empresa":{"cnpj":"25773037000183","razaoSocial":"PHARMASCIENCE INDUSTRIA FARMACEUTICA S.A","numeroAutorizacao":"1017173","cnpjFormatado":"25.773.037/0001-83"},"processo":{"numero":"25351478016201721","situacao":29,"numeroProcessoFormatado":"25351.478016/2017-21"}},{"ordem":58,"produto":{"codigo":284557,"nome":"QUADRINAX","numeroRegistro":"117170046","tipo":{"codigo":1,"descricao":null},"categoria":null,"situacaoRotulo":null,"dataVencimento":null,"mesAnoVencimento":"092008","dataVencimentoRegistro":"2008-09-01T00:00:00.000-0300","principioAtivo":null,"situacaoApresentacao":"Caduco/Cancelado","dataRegistro":"2003-09-23T00:00:00.000-0300","categoriaRegulatoria":{"codigo":8,"descricao":"Similar"},"medicamentoReferencia":null,"categoriaProduto":null,"tipoAutorizacao":"REGISTRADO","numeroRegistroFormatado":"117170046","mesAnoVencimentoFormatado":"09/2008","acancelar":false},"empresa":{"cnpj":"25773037000183","razaoSocial":"PHARMASCIENCE INDUSTRIA FARMACEUTICA S.A","numeroAutorizacao":"1017173","cnpjFormatado":"25.773.037/0001-83"},"processo":{"numero":"25351024474200349","situacao":29,"numeroProcessoFormatado":"25351.024474/2003-49"}},{"ordem":59,"produto":{"codigo":6714,"nome":"RESFEDRYL","numeroRegistro":"117170010","tipo":{"codigo":1,"descricao":null},"categoria":null,"situacaoRotulo":null,"dataVencimento":"2004-07-15T00:00:00.000-0300","mesAnoVencimento":"072029","dataVencimentoRegistro":"2029-07-01T00:00:00.000-0300","principioAtivo":"PARACETAMOL, MALEATO DE CLORFENAMINA, CLORIDRATO DE FENILEFRINA","situacaoApresentacao":"Válido","dataRegistro":"1999-07-15T00:00:00.000-0300","categoriaRegulatoria":{"codigo":8,"descricao":"Similar"},"medicamentoReferencia":null,"categoriaProduto":null,"tipoAutorizacao":"REGISTRADO","numeroRegistroFormatado":"117170010","mesAnoVencimentoFormatado":"07/2029","acancelar":false},"empresa":{"cnpj":"25773037000183","razaoSocial":"PHARMASCIENCE INDUSTRIA FARMACEUTICA S.A","numeroAutorizacao":"1017173","cnpjFormatado":"25.773.037/0001-83"},"processo":{"numero":"250000162539877","situacao":29,"numeroProcessoFormatado":"25000.016253/98-77"}},{"ordem":60,"produto":{"codigo":432556,"nome":"RITCOR","numeroRegistro":"117170038","tipo":{"codigo":1,"descricao":null},"categoria":null,"situacaoRotulo":null,"dataVencimento":null,"mesAnoVencimento":"092010","dataVencimentoRegistro":"2010-09-01T00:00:00.000-0300","principioAtivo":null,"situacaoApresentacao":"Caduco/Cancelado","dataRegistro":"2000-09-20T00:00:00.000-0300","categoriaRegulatoria":{"codigo":8,"descricao":"Similar"},"medicamentoReferencia":null,"categoriaProduto":null,"tipoAutorizacao":"REGISTRADO","numeroRegistroFormatado":"117170038","mesAnoVencimentoFormatado":"09/2010","acancelar":false},"empresa":{"cnpj":"25773037000183","razaoSocial":"PHARMASCIENCE INDUSTRIA FARMACEUTICA S.A","numeroAutorizacao":"1017173","cnpjFormatado":"25.773.037/0001-83"},"processo":{"numero":"250000554979992","situacao":29,"numeroProcessoFormatado":"25000.055497/99-92"}},{"ordem":61,"produto":{"codigo":1405,"nome":"RITPRESS","numeroRegistro":"117170030","tipo":{"codigo":1,"descricao":null},"categoria":null,"situacaoRotulo":null,"dataVencimento":null,"mesAnoVencimento":"072015","dataVencimentoRegistro":"2015-07-01T00:00:00.000-0300","principioAtivo":null,"situacaoApresentacao":"Caduco/Cancelado","dataRegistro":"2000-07-20T00:00:00.000-0300","categoriaRegulatoria":{"codigo":8,"descricao":"Similar"},"medicamentoReferencia":null,"categoriaProduto":null,"tipoAutorizacao":"REGISTRADO","numeroRegistroFormatado":"117170030","mesAnoVencimentoFormatado":"07/2015","acancelar":false},"empresa":{"cnpj":"25773037000183","razaoSocial":"PHARMASCIENCE INDUSTRIA FARMACEUTICA S.A","numeroAutorizacao":"1017173","cnpjFormatado":"25.773.037/0001-83"},"processo":{"numero":"250000555009903","situacao":29,"numeroProcessoFormatado":"25000.055500/99-03"}},{"ordem":62,"produto":{"codigo":2263,"nome":"SORINAN","numeroRegistro":"117170006","tipo":{"codigo":1,"descricao":null},"categoria":null,"situacaoRotulo":null,"dataVencimento":null,"mesAnoVencimento":"012028","dataVencimentoRegistro":"2028-01-01T00:00:00.000-0300","principioAtivo":"CLORETO DE BENZALCÔNIO, CLORIDRATO DE NAFAZOLINA, CLORETO DE SÓDIO","situacaoApresentacao":"Válido","dataRegistro":"1998-01-16T00:00:00.000-0300","categoriaRegulatoria":{"codigo":8,"descricao":"Similar"},"medicamentoReferencia":"SORINE","categoriaProduto":null,"tipoAutorizacao":"REGISTRADO","numeroRegistroFormatado":"117170006","mesAnoVencimentoFormatado":"01/2028","acancelar":false},"empresa":{"cnpj":"25773037000183","razaoSocial":"PHARMASCIENCE INDUSTRIA FARMACEUTICA S.A","numeroAutorizacao":"1017173","cnpjFormatado":"25.773.037/0001-83"},"processo":{"numero":"250000176369791","situacao":29,"numeroProcessoFormatado":"25000.017636/97-91"}},{"ordem":63,"produto":{"codigo":2240,"nome":"SORINAN INFANTIL","numeroRegistro":"117170003","tipo":{"codigo":1,"descricao":null},"categoria":null,"situacaoRotulo":null,"dataVencimento":null,"mesAnoVencimento":"122012","dataVencimentoRegistro":"2012-12-01T00:00:00.000-0300","principioAtivo":null,"situacaoApresentacao":"Caduco/Cancelado","dataRegistro":"1997-12-15T00:00:00.000-0300","categoriaRegulatoria":{"codigo":8,"descricao":"Similar"},"medicamentoReferencia":null,"categoriaProduto":null,"tipoAutorizacao":"REGISTRADO","numeroRegistroFormatado":"117170003","mesAnoVencimentoFormatado":"12/2012","acancelar":false},"empresa":{"cnpj":"25773037000183","razaoSocial":"PHARMASCIENCE INDUSTRIA FARMACEUTICA S.A","numeroAutorizacao":"1017173","cnpjFormatado":"25.773.037/0001-83"},"processo":{"numero":"250000410009651","situacao":29,"numeroProcessoFormatado":"25000.041000/96-51"}},{"ordem":64,"produto":{"codigo":436814,"nome":"SOYNATI","numeroRegistro":"117170062","tipo":{"codigo":1,"descricao":null},"categoria":null,"situacaoRotulo":null,"dataVencimento":null,"mesAnoVencimento":"012026","dataVencimentoRegistro":"2026-01-01T00:00:00.000-0300","principioAtivo":"GLYCINE MAX (L.) MERR.","situacaoApresentacao":"Válido","dataRegistro":"2006-01-30T00:00:00.000-0300","categoriaRegulatoria":{"codigo":4,"descricao":"Fitoterápico"},"medicamentoReferencia":null,"categoriaProduto":null,"tipoAutorizacao":"REGISTRADO","numeroRegistroFormatado":"117170062","mesAnoVencimentoFormatado":"01/2026","acancelar":false},"empresa":{"cnpj":"25773037000183","razaoSocial":"PHARMASCIENCE INDUSTRIA FARMACEUTICA S.A","numeroAutorizacao":"1017173","cnpjFormatado":"25.773.037/0001-83"},"processo":{"numero":"25351408281200517","situacao":29,"numeroProcessoFormatado":"25351.408281/2005-17"}},{"ordem":65,"produto":{"codigo":8057,"nome":"SPECTORUB","numeroRegistro":"117170033","tipo":{"codigo":1,"descricao":null},"categoria":null,"situacaoRotulo":null,"dataVencimento":null,"mesAnoVencimento":"092005","dataVencimentoRegistro":"2005-09-01T00:00:00.000-0300","principioAtivo":null,"situacaoApresentacao":"Caduco/Cancelado","dataRegistro":"2000-09-20T00:00:00.000-0300","categoriaRegulatoria":{"codigo":8,"descricao":"Similar"},"medicamentoReferencia":null,"categoriaProduto":null,"tipoAutorizacao":"REGISTRADO","numeroRegistroFormatado":"117170033","mesAnoVencimentoFormatado":"09/2005","acancelar":false},"empresa":{"cnpj":"25773037000183","razaoSocial":"PHARMASCIENCE INDUSTRIA FARMACEUTICA S.A","numeroAutorizacao":"1017173","cnpjFormatado":"25.773.037/0001-83"},"processo":{"numero":"250000551859970","situacao":29,"numeroProcessoFormatado":"25000.055185/99-70"}},{"ordem":66,"produto":{"codigo":5033,"nome":"SPECTOSAN","numeroRegistro":"117170004","tipo":{"codigo":1,"descricao":null},"categoria":null,"situacaoRotulo":null,"dataVencimento":null,"mesAnoVencimento":"122007","dataVencimentoRegistro":"2007-12-01T00:00:00.000-0300","principioAtivo":null,"situacaoApresentacao":"Caduco/Cancelado","dataRegistro":"1997-12-15T00:00:00.000-0300","categoriaRegulatoria":{"codigo":8,"descricao":"Similar"},"medicamentoReferencia":null,"categoriaProduto":null,"tipoAutorizacao":"REGISTRADO","numeroRegistroFormatado":"117170004","mesAnoVencimentoFormatado":"12/2007","acancelar":false},"empresa":{"cnpj":"25773037000183","razaoSocial":"PHARMASCIENCE INDUSTRIA FARMACEUTICA S.A","numeroAutorizacao":"1017173","cnpjFormatado":"25.773.037/0001-83"},"processo":{"numero":"250000410059675","situacao":29,"numeroProcessoFormatado":"25000.041005/96-75"}},{"ordem":67,"produto":{"codigo":374740,"nome":"SULFTRIN","numeroRegistro":"117170056","tipo":{"codigo":1,"descricao":null},"categoria":null,"situacaoRotulo":null,"dataVencimento":null,"mesAnoVencimento":"082010","dataVencimentoRegistro":"2010-08-01T00:00:00.000-0300","principioAtivo":null,"situacaoApresentacao":"Caduco/Cancelado","dataRegistro":"2005-08-15T00:00:00.000-0300","categoriaRegulatoria":{"codigo":8,"descricao":"Similar"},"medicamentoReferencia":null,"categoriaProduto":null,"tipoAutorizacao":"REGISTRADO","numeroRegistroFormatado":"117170056","mesAnoVencimentoFormatado":"08/2010","acancelar":false},"empresa":{"cnpj":"25773037000183","razaoSocial":"PHARMASCIENCE INDUSTRIA FARMACEUTICA S.A","numeroAutorizacao":"1017173","cnpjFormatado":"25.773.037/0001-83"},"processo":{"numero":"253510031110281","situacao":29,"numeroProcessoFormatado":"25351.003111/02-81"}},{"ordem":68,"produto":{"codigo":6985,"nome":"TONGIFORT","numeroRegistro":"117170039","tipo":{"codigo":1,"descricao":null},"categoria":null,"situacaoRotulo":null,"dataVencimento":null,"mesAnoVencimento":"012011","dataVencimentoRegistro":"2011-01-01T00:00:00.000-0300","principioAtivo":null,"situacaoApresentacao":"Caduco/Cancelado","dataRegistro":"2001-01-24T00:00:00.000-0300","categoriaRegulatoria":{"codigo":8,"descricao":"Similar"},"medicamentoReferencia":null,"categoriaProduto":null,"tipoAutorizacao":"REGISTRADO","numeroRegistroFormatado":"117170039","mesAnoVencimentoFormatado":"01/2011","acancelar":false},"empresa":{"cnpj":"25773037000183","razaoSocial":"PHARMASCIENCE INDUSTRIA FARMACEUTICA S.A","numeroAutorizacao":"1017173","cnpjFormatado":"25.773.037/0001-83"},"processo":{"numero":"250000309889722","situacao":29,"numeroProcessoFormatado":"25000.030988/97-22"}},{"ordem":69,"produto":{"codigo":6599,"nome":"TYLOL","numeroRegistro":"117170012","tipo":{"codigo":1,"descricao":null},"categoria":null,"situacaoRotulo":null,"dataVencimento":null,"mesAnoVencimento":"092009","dataVencimentoRegistro":"2009-09-01T00:00:00.000-0300","principioAtivo":null,"situacaoApresentacao":"Caduco/Cancelado","dataRegistro":"1999-09-22T00:00:00.000-0300","categoriaRegulatoria":{"codigo":8,"descricao":"Similar"},"medicamentoReferencia":null,"categoriaProduto":null,"tipoAutorizacao":"REGISTRADO","numeroRegistroFormatado":"117170012","mesAnoVencimentoFormatado":"09/2009","acancelar":false},"empresa":{"cnpj":"25773037000183","razaoSocial":"PHARMASCIENCE INDUSTRIA FARMACEUTICA S.A","numeroAutorizacao":"1017173","cnpjFormatado":"25.773.037/0001-83"},"processo":{"numero":"250000013799982","situacao":29,"numeroProcessoFormatado":"25000.001379/99-82"}},{"ordem":70,"produto":{"codigo":456757,"nome":"VALERINATI","numeroRegistro":"117170063","tipo":{"codigo":1,"descricao":null},"categoria":null,"situacaoRotulo":null,"dataVencimento":null,"mesAnoVencimento":"062026","dataVencimentoRegistro":"2026-06-01T00:00:00.000-0300","principioAtivo":"VALERIANA OFFICINALIS L.","situacaoApresentacao":"Válido","dataRegistro":"2006-06-19T00:00:00.000-0300","categoriaRegulatoria":{"codigo":4,"descricao":"Fitoterápico"},"medicamentoReferencia":null,"categoriaProduto":null,"tipoAutorizacao":"REGISTRADO","numeroRegistroFormatado":"117170063","mesAnoVencimentoFormatado":"06/2026","acancelar":false},"empresa":{"cnpj":"25773037000183","razaoSocial":"PHARMASCIENCE INDUSTRIA FARMACEUTICA S.A","numeroAutorizacao":"1017173","cnpjFormatado":"25.773.037/0001-83"},"processo":{"numero":"25351127977200618","situacao":29,"numeroProcessoFormatado":"25351.127977/2006-18"}},{"ordem":71,"produto":{"codigo":921309,"nome":"VARINATI","numeroRegistro":"117170076","tipo":{"codigo":1,"descricao":null},"categoria":null,"situacaoRotulo":null,"dataVencimento":null,"mesAnoVencimento":"102028","dataVencimentoRegistro":"2028-10-01T00:00:00.000-0300","principioAtivo":"AESCULUS HIPPOCASTANUM L.","situacaoApresentacao":"Válido","dataRegistro":"2013-10-14T00:00:00.000-0300","categoriaRegulatoria":{"codigo":4,"descricao":"Fitoterápico"},"medicamentoReferencia":null,"categoriaProduto":null,"tipoAutorizacao":"REGISTRADO","numeroRegistroFormatado":"117170076","mesAnoVencimentoFormatado":"10/2028","acancelar":false},"empresa":{"cnpj":"25773037000183","razaoSocial":"PHARMASCIENCE INDUSTRIA FARMACEUTICA S.A","numeroAutorizacao":"1017173","cnpjFormatado":"25.773.037/0001-83"},"processo":{"numero":"25351252700201388","situacao":29,"numeroProcessoFormatado":"25351.252700/2013-88"}},{"ordem":72,"produto":{"codigo":419758,"nome":"VARITRAT","numeroRegistro":"117170060","tipo":{"codigo":1,"descricao":null},"categoria":null,"situacaoRotulo":null,"dataVencimento":null,"mesAnoVencimento":"112010","dataVencimentoRegistro":"2010-11-01T00:00:00.000-0300","principioAtivo":null,"situacaoApresentacao":"Caduco/Cancelado","dataRegistro":"2005-11-07T00:00:00.000-0300","categoriaRegulatoria":{"codigo":4,"descricao":"Fitoterápico"},"medicamentoReferencia":null,"categoriaProduto":null,"tipoAutorizacao":"REGISTRADO","numeroRegistroFormatado":"117170060","mesAnoVencimentoFormatado":"11/2010","acancelar":false},"empresa":{"cnpj":"25773037000183","razaoSocial":"PHARMASCIENCE INDUSTRIA FARMACEUTICA S.A","numeroAutorizacao":"1017173","cnpjFormatado":"25.773.037/0001-83"},"processo":{"numero":"25351006335200503","situacao":29,"numeroProcessoFormatado":"25351.006335/2005-03"}},{"ordem":73,"produto":{"codigo":5751,"nome":"VASOVIRIL","numeroRegistro":"117170037","tipo":{"codigo":1,"descricao":null},"categoria":null,"situacaoRotulo":null,"dataVencimento":null,"mesAnoVencimento":"112010","dataVencimentoRegistro":"2010-11-01T00:00:00.000-0300","principioAtivo":null,"situacaoApresentacao":"Caduco/Cancelado","dataRegistro":"2000-11-10T00:00:00.000-0300","categoriaRegulatoria":{"codigo":8,"descricao":"Similar"},"medicamentoReferencia":null,"categoriaProduto":null,"tipoAutorizacao":"REGISTRADO","numeroRegistroFormatado":"117170037","mesAnoVencimentoFormatado":"11/2010","acancelar":false},"empresa":{"cnpj":"25773037000183","razaoSocial":"PHARMASCIENCE INDUSTRIA FARMACEUTICA S.A","numeroAutorizacao":"1017173","cnpjFormatado":"25.773.037/0001-83"},"processo":{"numero":"250000552349983","situacao":29,"numeroProcessoFormatado":"25000.055234/99-83"}},{"ordem":74,"produto":{"codigo":993,"nome":"ZITROMICIN","numeroRegistro":"117170029","tipo":{"codigo":1,"descricao":null},"categoria":null,"situacaoRotulo":null,"dataVencimento":null,"mesAnoVencimento":"072005","dataVencimentoRegistro":"2005-07-01T00:00:00.000-0300","principioAtivo":null,"situacaoApresentacao":"Caduco/Cancelado","dataRegistro":"2000-07-20T00:00:00.000-0300","categoriaRegulatoria":{"codigo":8,"descricao":"Similar"},"medicamentoReferencia":null,"categoriaProduto":null,"tipoAutorizacao":"REGISTRADO","numeroRegistroFormatado":"117170029","mesAnoVencimentoFormatado":"07/2005","acancelar":false},"empresa":{"cnpj":"25773037000183","razaoSocial":"PHARMASCIENCE INDUSTRIA FARMACEUTICA S.A","numeroAutorizacao":"1017173","cnpjFormatado":"25.773.037/0001-83"},"processo":{"numero":"250000552159939","situacao":29,"numeroProcessoFormatado":"25000.055215/99-39"}},{"ordem":75,"produto":{"codigo":596359,"nome":"ZITROMICIN","numeroRegistro":"117170071","tipo":{"codigo":1,"descricao":null},"categoria":null,"situacaoRotulo":null,"dataVencimento":null,"mesAnoVencimento":"102014","dataVencimentoRegistro":"2014-10-01T00:00:00.000-0300","principioAtivo":null,"situacaoApresentacao":"Caduco/Cancelado","dataRegistro":"2009-10-05T00:00:00.000-0300","categoriaRegulatoria":{"codigo":8,"descricao":"Similar"},"medicamentoReferencia":null,"categoriaProduto":null,"tipoAutorizacao":"REGISTRADO","numeroRegistroFormatado":"117170071","mesAnoVencimentoFormatado":"10/2014","acancelar":false},"empresa":{"cnpj":"25773037000183","razaoSocial":"PHARMASCIENCE INDUSTRIA FARMACEUTICA S.A","numeroAutorizacao":"1017173","cnpjFormatado":"25.773.037/0001-83"},"processo":{"numero":"25351446885200804","situacao":29,"numeroProcessoFormatado":"25351.446885/2008-04"}},{"ordem":76,"produto":{"codigo":802853,"nome":"cloridrato de fluoxetina","numeroRegistro":"117170077","tipo":{"codigo":1,"descricao":null},"categoria":null,"situacaoRotulo":null,"dataVencimento":null,"mesAnoVencimento":"122025","dataVencimentoRegistro":"2025-12-01T00:00:00.000-0300","principioAtivo":"CLORIDRATO DE FLUOXETINA","situacaoApresentacao":"Válido","dataRegistro":"2015-12-07T00:00:00.000-0300","categoriaRegulatoria":{"codigo":5,"descricao":"Genérico"},"medicamentoReferencia":"PROZAC","categoriaProduto":null,"tipoAutorizacao":"REGISTRADO","numeroRegistroFormatado":"117170077","mesAnoVencimentoFormatado":"12/2025","acancelar":false},"empresa":{"cnpj":"25773037000183","razaoSocial":"PHARMASCIENCE INDUSTRIA FARMACEUTICA S.A","numeroAutorizacao":"1017173","cnpjFormatado":"25.773.037/0001-83"},"processo":{"numero":"25351765994201149","situacao":29,"numeroProcessoFormatado":"25351.765994/2011-49"}},{"ordem":77,"produto":{"codigo":1981014,"nome":"cloridrato de loperamida","numeroRegistro":"117170081","tipo":{"codigo":1,"descricao":null},"categoria":null,"situacaoRotulo":null,"dataVencimento":null,"mesAnoVencimento":"032031","dataVencimentoRegistro":"2031-03-01T00:00:00.000-0300","principioAtivo":"CLORIDRATO DE LOPERAMIDA","situacaoApresentacao":"Válido","dataRegistro":"2021-03-08T00:00:00.000-0300","categoriaRegulatoria":{"codigo":5,"descricao":"Genérico"},"medicamentoReferencia":"IMOSEC","categoriaProduto":null,"tipoAutorizacao":"REGISTRADO","numeroRegistroFormatado":"117170081","mesAnoVencimentoFormatado":"03/2031","acancelar":false},"empresa":{"cnpj":"25773037000183","razaoSocial":"PHARMASCIENCE INDUSTRIA FARMACEUTICA S.A","numeroAutorizacao":"1017173","cnpjFormatado":"25.773.037/0001-83"},"processo":{"numero":"25351379470202004","situacao":29,"numeroProcessoFormatado":"25351.379470/2020-04"}},{"ordem":78,"produto":{"codigo":1361549,"nome":"fosfomicina trometamol","numeroRegistro":"117170082","tipo":{"codigo":1,"descricao":null},"categoria":null,"situacaoRotulo":null,"dataVencimento":null,"mesAnoVencimento":"072031","dataVencimentoRegistro":"2031-07-01T00:00:00.000-0300","principioAtivo":"FOSFOMICINA TROMETAMOL","situacaoApresentacao":"Válido","dataRegistro":"2021-07-19T00:00:00.000-0300","categoriaRegulatoria":{"codigo":5,"descricao":"Genérico"},"medicamentoReferencia":"MONURIL","categoriaProduto":null,"tipoAutorizacao":"REGISTRADO","numeroRegistroFormatado":"117170082","mesAnoVencimentoFormatado":"07/2031","acancelar":false},"empresa":{"cnpj":"25773037000183","razaoSocial":"PHARMASCIENCE INDUSTRIA FARMACEUTICA S.A","numeroAutorizacao":"1017173","cnpjFormatado":"25.773.037/0001-83"},"processo":{"numero":"25351600309201963","situacao":29,"numeroProcessoFormatado":"25351.600309/2019-63"}},{"ordem":79,"produto":{"codigo":8457,"nome":"ÁCIDO SALICÍLICO + ÁCIDO LÁTICO","numeroRegistro":"117170031","tipo":{"codigo":1,"descricao":null},"categoria":null,"situacaoRotulo":null,"dataVencimento":null,"mesAnoVencimento":"072005","dataVencimentoRegistro":"2005-07-01T00:00:00.000-0300","principioAtivo":null,"situacaoApresentacao":"Caduco/Cancelado","dataRegistro":"2000-07-20T00:00:00.000-0300","categoriaRegulatoria":{"codigo":8,"descricao":"Similar"},"medicamentoReferencia":null,"categoriaProduto":null,"tipoAutorizacao":"REGISTRADO","numeroRegistroFormatado":"117170031","mesAnoVencimentoFormatado":"07/2005","acancelar":false},"empresa":{"cnpj":"25773037000183","razaoSocial":"PHARMASCIENCE INDUSTRIA FARMACEUTICA S.A","numeroAutorizacao":"1017173","cnpjFormatado":"25.773.037/0001-83"},"processo":{"numero":"250000555019968","situacao":29,"numeroProcessoFormatado":"25000.055501/99-68"}}],"totalPages":1,"totalElements":79,"last":true,"numberOfElements":79,"size":1000,"number":0,"first":true,"sort":null}