{"content":[{"ordem":1,"produto":{"codigo":3127,"nome":"CORYNEBACTERIUM PARVUM","numeroRegistro":"101660003","tipo":{"codigo":1,"descricao":null},"categoria":null,"situacaoRotulo":null,"dataVencimento":null,"mesAnoVencimento":"082001","dataVencimentoRegistro":"2001-08-01T00:00:00.000-0300","principioAtivo":null,"situacaoApresentacao":"Caduco/Cancelado","dataRegistro":"2000-05-04T00:00:00.000-0300","categoriaRegulatoria":{"codigo":8,"descricao":"Similar"},"medicamentoReferencia":null,"categoriaProduto":null,"tipoAutorizacao":"REGISTRADO","mesAnoVencimentoFormatado":"08/2001","numeroRegistroFormatado":"101660003","acancelar":false},"empresa":{"cnpj":"33485939000142","razaoSocial":"FUNDACAO ATAULPHO DE PAIVA","numeroAutorizacao":"1001663","cnpjFormatado":"33.485.939/0001-42"},"processo":{"numero":"2500100272385","situacao":29,"numeroProcessoFormatado":"25001.002723/85"}},{"ordem":2,"produto":{"codigo":4027,"nome":"EXTRATO DE TIMO","numeroRegistro":"101660004","tipo":{"codigo":1,"descricao":null},"categoria":null,"situacaoRotulo":null,"dataVencimento":null,"mesAnoVencimento":"042004","dataVencimentoRegistro":"2004-04-01T00:00:00.000-0300","principioAtivo":null,"situacaoApresentacao":"Caduco/Cancelado","dataRegistro":"2000-05-04T00:00:00.000-0300","categoriaRegulatoria":{"codigo":8,"descricao":"Similar"},"medicamentoReferencia":null,"categoriaProduto":null,"tipoAutorizacao":"REGISTRADO","mesAnoVencimentoFormatado":"04/2004","numeroRegistroFormatado":"101660004","acancelar":false},"empresa":{"cnpj":"33485939000142","razaoSocial":"FUNDACAO ATAULPHO DE PAIVA","numeroAutorizacao":"1001663","cnpjFormatado":"33.485.939/0001-42"},"processo":{"numero":"2500100576986","situacao":29,"numeroProcessoFormatado":"25001.005769/86"}},{"ordem":3,"produto":{"codigo":368380,"nome":"IMUNO  BCG","numeroRegistro":"101660016","tipo":{"codigo":1,"descricao":null},"categoria":null,"situacaoRotulo":null,"dataVencimento":null,"mesAnoVencimento":"092024","dataVencimentoRegistro":"2024-09-01T00:00:00.000-0300","principioAtivo":"Mycobacterium bovis","situacaoApresentacao":"Válido","dataRegistro":"2004-10-04T00:00:00.000-0300","categoriaRegulatoria":{"codigo":1,"descricao":"Biológico"},"medicamentoReferencia":null,"categoriaProduto":null,"tipoAutorizacao":"REGISTRADO","mesAnoVencimentoFormatado":"09/2024","numeroRegistroFormatado":"101660016","acancelar":false},"empresa":{"cnpj":"33485939000142","razaoSocial":"FUNDACAO ATAULPHO DE PAIVA","numeroAutorizacao":"1001663","cnpjFormatado":"33.485.939/0001-42"},"processo":{"numero":"25351035626200339","situacao":29,"numeroProcessoFormatado":"25351.035626/2003-39"}},{"ordem":4,"produto":{"codigo":125848,"nome":"IMUNOESTIMULANTE BACILO DE CALMETTE -GUERIN ( BCG)","numeroRegistro":"101660012","tipo":{"codigo":1,"descricao":null},"categoria":null,"situacaoRotulo":null,"dataVencimento":null,"mesAnoVencimento":"052007","dataVencimentoRegistro":"2007-05-01T00:00:00.000-0300","principioAtivo":null,"situacaoApresentacao":"Caduco/Cancelado","dataRegistro":"2002-05-09T00:00:00.000-0300","categoriaRegulatoria":{"codigo":8,"descricao":"Similar"},"medicamentoReferencia":null,"categoriaProduto":null,"tipoAutorizacao":"REGISTRADO","mesAnoVencimentoFormatado":"05/2007","numeroRegistroFormatado":"101660012","acancelar":false},"empresa":{"cnpj":"33485939000142","razaoSocial":"FUNDACAO ATAULPHO DE PAIVA","numeroAutorizacao":"1001663","cnpjFormatado":"33.485.939/0001-42"},"processo":{"numero":"253510099230169","situacao":29,"numeroProcessoFormatado":"25351.009923/01-69"}},{"ordem":5,"produto":{"codigo":366176,"nome":"VACINA BCG","numeroRegistro":"101660017","tipo":{"codigo":1,"descricao":null},"categoria":null,"situacaoRotulo":null,"dataVencimento":null,"mesAnoVencimento":"062028","dataVencimentoRegistro":"2028-06-01T00:00:00.000-0300","principioAtivo":"VACINA BCG","situacaoApresentacao":"Válido","dataRegistro":"1988-06-30T00:00:00.000-0300","categoriaRegulatoria":{"codigo":null,"descricao":null},"medicamentoReferencia":null,"categoriaProduto":null,"tipoAutorizacao":"REGISTRADO","mesAnoVencimentoFormatado":"06/2028","numeroRegistroFormatado":"101660017","acancelar":false},"empresa":{"cnpj":"33485939000142","razaoSocial":"FUNDACAO ATAULPHO DE PAIVA","numeroAutorizacao":"1001663","cnpjFormatado":"33.485.939/0001-42"},"processo":{"numero":"2599201017370","situacao":29,"numeroProcessoFormatado":"25992.010173/70"}}],"totalPages":1,"totalElements":5,"last":true,"numberOfElements":5,"first":true,"sort":null,"size":1000,"number":0}