{"content":[{"ordem":1,"produto":{"codigo":297,"nome":"ACICLOVIR","numeroRegistro":"104300016","tipo":{"codigo":1,"descricao":null},"categoria":null,"situacaoRotulo":null,"dataVencimento":null,"mesAnoVencimento":"082003","dataVencimentoRegistro":"2003-08-01T00:00:00.000-0300","principioAtivo":null,"situacaoApresentacao":"Caduco/Cancelado","dataRegistro":"1998-08-24T00:00:00.000-0300","categoriaRegulatoria":{"codigo":8,"descricao":"Similar"},"medicamentoReferencia":null,"categoriaProduto":null,"tipoAutorizacao":"REGISTRADO","acancelar":false,"mesAnoVencimentoFormatado":"08/2003","numeroRegistroFormatado":"104300016"},"empresa":{"cnpj":"42457796000156","razaoSocial":"DIFFUCAP - CHEMOBRÁS QUÍMICA E FARMACÊUTICA LTDA","numeroAutorizacao":"1004304","cnpjFormatado":"42.457.796/0001-56"},"processo":{"numero":"250000080269850","situacao":29,"numeroProcessoFormatado":"25000.008026/98-50"}},{"ordem":2,"produto":{"codigo":2491,"nome":"AKALURET","numeroRegistro":"104300023","tipo":{"codigo":1,"descricao":null},"categoria":null,"situacaoRotulo":null,"dataVencimento":null,"mesAnoVencimento":"072005","dataVencimentoRegistro":"2005-07-01T00:00:00.000-0300","principioAtivo":null,"situacaoApresentacao":"Caduco/Cancelado","dataRegistro":"2000-07-13T00:00:00.000-0300","categoriaRegulatoria":{"codigo":8,"descricao":"Similar"},"medicamentoReferencia":null,"categoriaProduto":null,"tipoAutorizacao":"REGISTRADO","acancelar":false,"mesAnoVencimentoFormatado":"07/2005","numeroRegistroFormatado":"104300023"},"empresa":{"cnpj":"42457796000156","razaoSocial":"DIFFUCAP - CHEMOBRÁS QUÍMICA E FARMACÊUTICA LTDA","numeroAutorizacao":"1004304","cnpjFormatado":"42.457.796/0001-56"},"processo":{"numero":"250000087439971","situacao":29,"numeroProcessoFormatado":"25000.008743/99-71"}},{"ordem":3,"produto":{"codigo":1287966,"nome":"ANGIOPRIL","numeroRegistro":"104300042","tipo":{"codigo":1,"descricao":null},"categoria":null,"situacaoRotulo":null,"dataVencimento":"2028-12-02T00:00:00.000-0300","mesAnoVencimento":"122028","dataVencimentoRegistro":"2028-12-01T00:00:00.000-0300","principioAtivo":null,"situacaoApresentacao":"Caduco/Cancelado","dataRegistro":"2018-12-17T00:00:00.000-0300","categoriaRegulatoria":{"codigo":8,"descricao":"Similar"},"medicamentoReferencia":"RENITEC","categoriaProduto":null,"tipoAutorizacao":"REGISTRADO","acancelar":false,"mesAnoVencimentoFormatado":"12/2028","numeroRegistroFormatado":"104300042"},"empresa":{"cnpj":"42457796000156","razaoSocial":"DIFFUCAP - CHEMOBRÁS QUÍMICA E FARMACÊUTICA LTDA","numeroAutorizacao":"1004304","cnpjFormatado":"42.457.796/0001-56"},"processo":{"numero":"25351390554201876","situacao":29,"numeroProcessoFormatado":"25351.390554/2018-76"}},{"ordem":4,"produto":{"codigo":3653714,"nome":"ANGIOPRIL","numeroRegistro":"104300046","tipo":{"codigo":1,"descricao":null},"categoria":null,"situacaoRotulo":null,"dataVencimento":"2033-10-19T00:00:00.000-0300","mesAnoVencimento":"102033","dataVencimentoRegistro":"2033-10-01T00:00:00.000-0300","principioAtivo":"MALEATO DE ENALAPRIL","situacaoApresentacao":"Válido","dataRegistro":"2023-10-19T00:00:00.000-0300","categoriaRegulatoria":{"codigo":8,"descricao":"Similar"},"medicamentoReferencia":"Renitec","categoriaProduto":null,"tipoAutorizacao":"REGISTRADO","acancelar":false,"mesAnoVencimentoFormatado":"10/2033","numeroRegistroFormatado":"104300046"},"empresa":{"cnpj":"42457796000156","razaoSocial":"DIFFUCAP - CHEMOBRÁS QUÍMICA E FARMACÊUTICA LTDA","numeroAutorizacao":"1004304","cnpjFormatado":"42.457.796/0001-56"},"processo":{"numero":"25351151728202344","situacao":29,"numeroProcessoFormatado":"25351.151728/2023-44"}},{"ordem":5,"produto":{"codigo":5526,"nome":"ANGIOPRIL","numeroRegistro":"104300017","tipo":{"codigo":1,"descricao":null},"categoria":null,"situacaoRotulo":null,"dataVencimento":null,"mesAnoVencimento":"082023","dataVencimentoRegistro":"2023-08-01T00:00:00.000-0300","principioAtivo":null,"situacaoApresentacao":"Caduco/Cancelado","dataRegistro":"1998-08-24T00:00:00.000-0300","categoriaRegulatoria":{"codigo":8,"descricao":"Similar"},"medicamentoReferencia":null,"categoriaProduto":null,"tipoAutorizacao":"REGISTRADO","acancelar":false,"mesAnoVencimentoFormatado":"08/2023","numeroRegistroFormatado":"104300017"},"empresa":{"cnpj":"42457796000156","razaoSocial":"DIFFUCAP - CHEMOBRÁS QUÍMICA E FARMACÊUTICA LTDA","numeroAutorizacao":"1004304","cnpjFormatado":"42.457.796/0001-56"},"processo":{"numero":"250000080219836","situacao":29,"numeroProcessoFormatado":"25000.008021/98-36"}},{"ordem":6,"produto":{"codigo":6158,"nome":"ARFLEX","numeroRegistro":"104300020","tipo":{"codigo":1,"descricao":null},"categoria":null,"situacaoRotulo":null,"dataVencimento":null,"mesAnoVencimento":"052014","dataVencimentoRegistro":"2014-05-01T00:00:00.000-0300","principioAtivo":null,"situacaoApresentacao":"Caduco/Cancelado","dataRegistro":"1999-05-24T00:00:00.000-0300","categoriaRegulatoria":{"codigo":8,"descricao":"Similar"},"medicamentoReferencia":null,"categoriaProduto":null,"tipoAutorizacao":"REGISTRADO","acancelar":false,"mesAnoVencimentoFormatado":"05/2014","numeroRegistroFormatado":"104300020"},"empresa":{"cnpj":"42457796000156","razaoSocial":"DIFFUCAP - CHEMOBRÁS QUÍMICA E FARMACÊUTICA LTDA","numeroAutorizacao":"1004304","cnpjFormatado":"42.457.796/0001-56"},"processo":{"numero":"250000297999752","situacao":29,"numeroProcessoFormatado":"25000.029799/97-52"}},{"ordem":7,"produto":{"codigo":750335,"nome":"ARFLEX RETARD","numeroRegistro":"104300041","tipo":{"codigo":1,"descricao":null},"categoria":null,"situacaoRotulo":null,"dataVencimento":null,"mesAnoVencimento":"052029","dataVencimentoRegistro":"2029-05-01T00:00:00.000-0300","principioAtivo":"NIMESULIDA","situacaoApresentacao":"Válido","dataRegistro":"2011-05-02T00:00:00.000-0300","categoriaRegulatoria":{"codigo":6,"descricao":"Novo"},"medicamentoReferencia":null,"categoriaProduto":null,"tipoAutorizacao":"REGISTRADO","acancelar":false,"mesAnoVencimentoFormatado":"05/2029","numeroRegistroFormatado":"104300041"},"empresa":{"cnpj":"42457796000156","razaoSocial":"DIFFUCAP - CHEMOBRÁS QUÍMICA E FARMACÊUTICA LTDA","numeroAutorizacao":"1004304","cnpjFormatado":"42.457.796/0001-56"},"processo":{"numero":"25351177429201181","situacao":29,"numeroProcessoFormatado":"25351.177429/2011-81"}},{"ordem":8,"produto":{"codigo":165140,"nome":"ATINAC","numeroRegistro":"104300011","tipo":{"codigo":1,"descricao":null},"categoria":null,"situacaoRotulo":null,"dataVencimento":null,"mesAnoVencimento":"062014","dataVencimentoRegistro":"2014-06-01T00:00:00.000-0300","principioAtivo":null,"situacaoApresentacao":"Caduco/Cancelado","dataRegistro":"1998-02-17T00:00:00.000-0300","categoriaRegulatoria":{"codigo":8,"descricao":"Similar"},"medicamentoReferencia":null,"categoriaProduto":null,"tipoAutorizacao":"REGISTRADO","acancelar":false,"mesAnoVencimentoFormatado":"06/2014","numeroRegistroFormatado":"104300011"},"empresa":{"cnpj":"42457796000156","razaoSocial":"DIFFUCAP - CHEMOBRÁS QUÍMICA E FARMACÊUTICA LTDA","numeroAutorizacao":"1004304","cnpjFormatado":"42.457.796/0001-56"},"processo":{"numero":"250000085959218","situacao":29,"numeroProcessoFormatado":"25000.008595/92-18"}},{"ordem":9,"produto":{"codigo":1231,"nome":"BROMAX","numeroRegistro":"104300024","tipo":{"codigo":1,"descricao":null},"categoria":null,"situacaoRotulo":null,"dataVencimento":null,"mesAnoVencimento":"072005","dataVencimentoRegistro":"2005-07-01T00:00:00.000-0300","principioAtivo":null,"situacaoApresentacao":"Caduco/Cancelado","dataRegistro":"2000-07-13T00:00:00.000-0300","categoriaRegulatoria":{"codigo":8,"descricao":"Similar"},"medicamentoReferencia":null,"categoriaProduto":null,"tipoAutorizacao":"REGISTRADO","acancelar":false,"mesAnoVencimentoFormatado":"07/2005","numeroRegistroFormatado":"104300024"},"empresa":{"cnpj":"42457796000156","razaoSocial":"DIFFUCAP - CHEMOBRÁS QUÍMICA E FARMACÊUTICA LTDA","numeroAutorizacao":"1004304","cnpjFormatado":"42.457.796/0001-56"},"processo":{"numero":"250000158589911","situacao":29,"numeroProcessoFormatado":"25000.015858/99-11"}},{"ordem":10,"produto":{"codigo":2109,"nome":"CHEMODOR","numeroRegistro":"104300026","tipo":{"codigo":1,"descricao":null},"categoria":null,"situacaoRotulo":null,"dataVencimento":null,"mesAnoVencimento":"092005","dataVencimentoRegistro":"2005-09-01T00:00:00.000-0300","principioAtivo":null,"situacaoApresentacao":"Caduco/Cancelado","dataRegistro":"2000-09-29T00:00:00.000-0300","categoriaRegulatoria":{"codigo":8,"descricao":"Similar"},"medicamentoReferencia":null,"categoriaProduto":null,"tipoAutorizacao":"REGISTRADO","acancelar":false,"mesAnoVencimentoFormatado":"09/2005","numeroRegistroFormatado":"104300026"},"empresa":{"cnpj":"42457796000156","razaoSocial":"DIFFUCAP - CHEMOBRÁS QUÍMICA E FARMACÊUTICA LTDA","numeroAutorizacao":"1004304","cnpjFormatado":"42.457.796/0001-56"},"processo":{"numero":"250000191329940","situacao":29,"numeroProcessoFormatado":"25000.019132/99-40"}},{"ordem":11,"produto":{"codigo":126407,"nome":"CORDIRON","numeroRegistro":"104300034","tipo":{"codigo":1,"descricao":null},"categoria":null,"situacaoRotulo":null,"dataVencimento":null,"mesAnoVencimento":"062022 ","dataVencimentoRegistro":"2022-06-01T00:00:00.000-0300","principioAtivo":null,"situacaoApresentacao":"Caduco/Cancelado","dataRegistro":"2002-06-05T00:00:00.000-0300","categoriaRegulatoria":{"codigo":8,"descricao":"Similar"},"medicamentoReferencia":null,"categoriaProduto":null,"tipoAutorizacao":"REGISTRADO","acancelar":false,"mesAnoVencimentoFormatado":"06/2022","numeroRegistroFormatado":"104300034"},"empresa":{"cnpj":"42457796000156","razaoSocial":"DIFFUCAP - CHEMOBRÁS QUÍMICA E FARMACÊUTICA LTDA","numeroAutorizacao":"1004304","cnpjFormatado":"42.457.796/0001-56"},"processo":{"numero":"250000087429917","situacao":29,"numeroProcessoFormatado":"25000.008742/99-17"}},{"ordem":12,"produto":{"codigo":5178,"nome":"DEOCIL","numeroRegistro":"104300032","tipo":{"codigo":1,"descricao":null},"categoria":null,"situacaoRotulo":null,"dataVencimento":null,"mesAnoVencimento":"122026","dataVencimentoRegistro":"2026-12-01T00:00:00.000-0300","principioAtivo":"CETOROLACO TROMETAMINA","situacaoApresentacao":"Válido","dataRegistro":"2001-12-27T00:00:00.000-0200","categoriaRegulatoria":{"codigo":8,"descricao":"Similar"},"medicamentoReferencia":"TORAGESIC","categoriaProduto":null,"tipoAutorizacao":"REGISTRADO","acancelar":false,"mesAnoVencimentoFormatado":"12/2026","numeroRegistroFormatado":"104300032"},"empresa":{"cnpj":"42457796000156","razaoSocial":"DIFFUCAP - CHEMOBRÁS QUÍMICA E FARMACÊUTICA LTDA","numeroAutorizacao":"1004304","cnpjFormatado":"42.457.796/0001-56"},"processo":{"numero":"253510159860163","situacao":29,"numeroProcessoFormatado":"25351.015986/01-63"}},{"ordem":13,"produto":{"codigo":3445,"nome":"DESINFLEX","numeroRegistro":"104300029","tipo":{"codigo":1,"descricao":null},"categoria":null,"situacaoRotulo":null,"dataVencimento":null,"mesAnoVencimento":"112010","dataVencimentoRegistro":"2010-11-01T00:00:00.000-0300","principioAtivo":null,"situacaoApresentacao":"Caduco/Cancelado","dataRegistro":"2000-11-09T00:00:00.000-0300","categoriaRegulatoria":{"codigo":8,"descricao":"Similar"},"medicamentoReferencia":null,"categoriaProduto":null,"tipoAutorizacao":"REGISTRADO","acancelar":false,"mesAnoVencimentoFormatado":"11/2010","numeroRegistroFormatado":"104300029"},"empresa":{"cnpj":"42457796000156","razaoSocial":"DIFFUCAP - CHEMOBRÁS QUÍMICA E FARMACÊUTICA LTDA","numeroAutorizacao":"1004304","cnpjFormatado":"42.457.796/0001-56"},"processo":{"numero":"250000087419946","situacao":29,"numeroProcessoFormatado":"25000.008741/99-46"}},{"ordem":14,"produto":{"codigo":3353,"nome":"DESINFLEX GEL","numeroRegistro":"104300028","tipo":{"codigo":1,"descricao":null},"categoria":null,"situacaoRotulo":null,"dataVencimento":null,"mesAnoVencimento":"112005","dataVencimentoRegistro":"2005-11-01T00:00:00.000-0300","principioAtivo":null,"situacaoApresentacao":"Caduco/Cancelado","dataRegistro":"2000-11-08T00:00:00.000-0300","categoriaRegulatoria":{"codigo":8,"descricao":"Similar"},"medicamentoReferencia":null,"categoriaProduto":null,"tipoAutorizacao":"REGISTRADO","acancelar":false,"mesAnoVencimentoFormatado":"11/2005","numeroRegistroFormatado":"104300028"},"empresa":{"cnpj":"42457796000156","razaoSocial":"DIFFUCAP - CHEMOBRÁS QUÍMICA E FARMACÊUTICA LTDA","numeroAutorizacao":"1004304","cnpjFormatado":"42.457.796/0001-56"},"processo":{"numero":"250000087389931","situacao":29,"numeroProcessoFormatado":"25000.008738/99-31"}},{"ordem":15,"produto":{"codigo":165088,"nome":"DESINFLEX RETARD","numeroRegistro":"104300038","tipo":{"codigo":1,"descricao":null},"categoria":null,"situacaoRotulo":null,"dataVencimento":null,"mesAnoVencimento":"102017","dataVencimentoRegistro":"2017-10-01T00:00:00.000-0300","principioAtivo":null,"situacaoApresentacao":"Caduco/Cancelado","dataRegistro":"2002-10-21T00:00:00.000-0300","categoriaRegulatoria":{"codigo":8,"descricao":"Similar"},"medicamentoReferencia":null,"categoriaProduto":null,"tipoAutorizacao":"REGISTRADO","acancelar":false,"mesAnoVencimentoFormatado":"10/2017","numeroRegistroFormatado":"104300038"},"empresa":{"cnpj":"42457796000156","razaoSocial":"DIFFUCAP - CHEMOBRÁS QUÍMICA E FARMACÊUTICA LTDA","numeroAutorizacao":"1004304","cnpjFormatado":"42.457.796/0001-56"},"processo":{"numero":"250010085138613","situacao":29,"numeroProcessoFormatado":"25001.008513/86-13"}},{"ordem":16,"produto":{"codigo":583401,"nome":"FLUXTAR","numeroRegistro":"104300040","tipo":{"codigo":1,"descricao":null},"categoria":null,"situacaoRotulo":null,"dataVencimento":null,"mesAnoVencimento":"012029","dataVencimentoRegistro":"2029-01-01T00:00:00.000-0300","principioAtivo":"BROMAZEPAM","situacaoApresentacao":"Válido","dataRegistro":"2009-01-12T00:00:00.000-0300","categoriaRegulatoria":{"codigo":8,"descricao":"Similar"},"medicamentoReferencia":"LEXOTAN CR","categoriaProduto":null,"tipoAutorizacao":"REGISTRADO","acancelar":false,"mesAnoVencimentoFormatado":"01/2029","numeroRegistroFormatado":"104300040"},"empresa":{"cnpj":"42457796000156","razaoSocial":"DIFFUCAP - CHEMOBRÁS QUÍMICA E FARMACÊUTICA LTDA","numeroAutorizacao":"1004304","cnpjFormatado":"42.457.796/0001-56"},"processo":{"numero":"25351225271200882","situacao":29,"numeroProcessoFormatado":"25351.225271/2008-82"}},{"ordem":17,"produto":{"codigo":462451,"nome":"LONCORD","numeroRegistro":"104300008","tipo":{"codigo":1,"descricao":null},"categoria":null,"situacaoRotulo":null,"dataVencimento":null,"mesAnoVencimento":"092027","dataVencimentoRegistro":"2027-09-01T00:00:00.000-0300","principioAtivo":"NIFEDIPINA","situacaoApresentacao":"Válido","dataRegistro":"1992-09-04T00:00:00.000-0300","categoriaRegulatoria":{"codigo":8,"descricao":"Similar"},"medicamentoReferencia":null,"categoriaProduto":null,"tipoAutorizacao":"REGISTRADO","acancelar":false,"mesAnoVencimentoFormatado":"09/2027","numeroRegistroFormatado":"104300008"},"empresa":{"cnpj":"42457796000156","razaoSocial":"DIFFUCAP - CHEMOBRÁS QUÍMICA E FARMACÊUTICA LTDA","numeroAutorizacao":"1004304","cnpjFormatado":"42.457.796/0001-56"},"processo":{"numero":"250000086049207","situacao":29,"numeroProcessoFormatado":"25000.008604/92-07"}},{"ordem":18,"produto":{"codigo":5162,"nome":"MICONAL","numeroRegistro":"104300031","tipo":{"codigo":1,"descricao":null},"categoria":null,"situacaoRotulo":null,"dataVencimento":null,"mesAnoVencimento":"122026","dataVencimentoRegistro":"2026-12-01T00:00:00.000-0300","principioAtivo":null,"situacaoApresentacao":"Caduco/Cancelado","dataRegistro":"2001-12-27T00:00:00.000-0200","categoriaRegulatoria":{"codigo":8,"descricao":"Similar"},"medicamentoReferencia":null,"categoriaProduto":null,"tipoAutorizacao":"REGISTRADO","acancelar":false,"mesAnoVencimentoFormatado":"12/2026","numeroRegistroFormatado":"104300031"},"empresa":{"cnpj":"42457796000156","razaoSocial":"DIFFUCAP - CHEMOBRÁS QUÍMICA E FARMACÊUTICA LTDA","numeroAutorizacao":"1004304","cnpjFormatado":"42.457.796/0001-56"},"processo":{"numero":"250000280939719","situacao":29,"numeroProcessoFormatado":"25000.028093/97-19"}},{"ordem":19,"produto":{"codigo":2314,"nome":"MUCOREX","numeroRegistro":"104300021","tipo":{"codigo":1,"descricao":null},"categoria":null,"situacaoRotulo":null,"dataVencimento":null,"mesAnoVencimento":"072009","dataVencimentoRegistro":"2009-07-01T00:00:00.000-0300","principioAtivo":null,"situacaoApresentacao":"Caduco/Cancelado","dataRegistro":"1999-08-25T00:00:00.000-0300","categoriaRegulatoria":{"codigo":8,"descricao":"Similar"},"medicamentoReferencia":null,"categoriaProduto":null,"tipoAutorizacao":"REGISTRADO","acancelar":false,"mesAnoVencimentoFormatado":"07/2009","numeroRegistroFormatado":"104300021"},"empresa":{"cnpj":"42457796000156","razaoSocial":"DIFFUCAP - CHEMOBRÁS QUÍMICA E FARMACÊUTICA LTDA","numeroAutorizacao":"1004304","cnpjFormatado":"42.457.796/0001-56"},"processo":{"numero":"250000087409983","situacao":29,"numeroProcessoFormatado":"25000.008740/99-83"}},{"ordem":20,"produto":{"codigo":1251278,"nome":"Maleato de enalapril","numeroRegistro":"104300044","tipo":{"codigo":1,"descricao":null},"categoria":null,"situacaoRotulo":null,"dataVencimento":null,"mesAnoVencimento":"102029","dataVencimentoRegistro":"2029-10-01T00:00:00.000-0300","principioAtivo":"MALEATO DE ENALAPRIL","situacaoApresentacao":"Válido","dataRegistro":"2019-10-29T00:00:00.000-0300","categoriaRegulatoria":{"codigo":5,"descricao":"Genérico"},"medicamentoReferencia":"Renitec","categoriaProduto":null,"tipoAutorizacao":"REGISTRADO","acancelar":false,"mesAnoVencimentoFormatado":"10/2029","numeroRegistroFormatado":"104300044"},"empresa":{"cnpj":"42457796000156","razaoSocial":"DIFFUCAP - CHEMOBRÁS QUÍMICA E FARMACÊUTICA LTDA","numeroAutorizacao":"1004304","cnpjFormatado":"42.457.796/0001-56"},"processo":{"numero":"25351245009201826","situacao":29,"numeroProcessoFormatado":"25351.245009/2018-26"}},{"ordem":21,"produto":{"codigo":1135,"nome":"NEMODINE","numeroRegistro":"104300018","tipo":{"codigo":1,"descricao":null},"categoria":null,"situacaoRotulo":null,"dataVencimento":null,"mesAnoVencimento":"102028","dataVencimentoRegistro":"2028-10-01T00:00:00.000-0300","principioAtivo":"BESILATO DE AMLODIPINA","situacaoApresentacao":"Válido","dataRegistro":"1998-10-02T00:00:00.000-0300","categoriaRegulatoria":{"codigo":8,"descricao":"Similar"},"medicamentoReferencia":null,"categoriaProduto":null,"tipoAutorizacao":"REGISTRADO","acancelar":false,"mesAnoVencimentoFormatado":"10/2028","numeroRegistroFormatado":"104300018"},"empresa":{"cnpj":"42457796000156","razaoSocial":"DIFFUCAP - CHEMOBRÁS QUÍMICA E FARMACÊUTICA LTDA","numeroAutorizacao":"1004304","cnpjFormatado":"42.457.796/0001-56"},"processo":{"numero":"250000333029746","situacao":29,"numeroProcessoFormatado":"25000.033302/97-46"}},{"ordem":22,"produto":{"codigo":346701,"nome":"NIMOVAS","numeroRegistro":"104300019","tipo":{"codigo":1,"descricao":null},"categoria":null,"situacaoRotulo":null,"dataVencimento":"2026-03-22T00:00:00.000-0300","mesAnoVencimento":"012029","dataVencimentoRegistro":"2029-01-01T00:00:00.000-0300","principioAtivo":null,"situacaoApresentacao":"Caduco/Cancelado","dataRegistro":"1999-01-12T00:00:00.000-0300","categoriaRegulatoria":{"codigo":8,"descricao":"Similar"},"medicamentoReferencia":null,"categoriaProduto":null,"tipoAutorizacao":"REGISTRADO","acancelar":false,"mesAnoVencimentoFormatado":"01/2029","numeroRegistroFormatado":"104300019"},"empresa":{"cnpj":"42457796000156","razaoSocial":"DIFFUCAP - CHEMOBRÁS QUÍMICA E FARMACÊUTICA LTDA","numeroAutorizacao":"1004304","cnpjFormatado":"42.457.796/0001-56"},"processo":{"numero":"250000268879710","situacao":29,"numeroProcessoFormatado":"25000.026887/97-10"}},{"ordem":23,"produto":{"codigo":8270,"nome":"NOVIDAT","numeroRegistro":"104300030","tipo":{"codigo":1,"descricao":null},"categoria":null,"situacaoRotulo":null,"dataVencimento":null,"mesAnoVencimento":"112010","dataVencimentoRegistro":"2010-11-01T00:00:00.000-0300","principioAtivo":null,"situacaoApresentacao":"Caduco/Cancelado","dataRegistro":"2000-11-20T00:00:00.000-0300","categoriaRegulatoria":{"codigo":8,"descricao":"Similar"},"medicamentoReferencia":null,"categoriaProduto":null,"tipoAutorizacao":"REGISTRADO","acancelar":false,"mesAnoVencimentoFormatado":"11/2010","numeroRegistroFormatado":"104300030"},"empresa":{"cnpj":"42457796000156","razaoSocial":"DIFFUCAP - CHEMOBRÁS QUÍMICA E FARMACÊUTICA LTDA","numeroAutorizacao":"1004304","cnpjFormatado":"42.457.796/0001-56"},"processo":{"numero":"253510077550012","situacao":29,"numeroProcessoFormatado":"25351.007755/00-12"}},{"ordem":24,"produto":{"codigo":3195815,"nome":"NYTEB","numeroRegistro":"104300045","tipo":{"codigo":1,"descricao":null},"categoria":null,"situacaoRotulo":null,"dataVencimento":null,"mesAnoVencimento":"042032","dataVencimentoRegistro":"2032-04-01T00:00:00.000-0300","principioAtivo":"cloridrato de nebivolol","situacaoApresentacao":"Válido","dataRegistro":"2022-04-04T00:00:00.000-0300","categoriaRegulatoria":{"codigo":8,"descricao":"Similar"},"medicamentoReferencia":"NEBILET","categoriaProduto":null,"tipoAutorizacao":"REGISTRADO","acancelar":false,"mesAnoVencimentoFormatado":"04/2032","numeroRegistroFormatado":"104300045"},"empresa":{"cnpj":"42457796000156","razaoSocial":"DIFFUCAP - CHEMOBRÁS QUÍMICA E FARMACÊUTICA LTDA","numeroAutorizacao":"1004304","cnpjFormatado":"42.457.796/0001-56"},"processo":{"numero":"25351014044202109","situacao":29,"numeroProcessoFormatado":"25351.014044/2021-09"}},{"ordem":25,"produto":{"codigo":6777,"nome":"PENTOXIFILINA","numeroRegistro":"104300025","tipo":{"codigo":1,"descricao":null},"categoria":null,"situacaoRotulo":null,"dataVencimento":null,"mesAnoVencimento":"072010","dataVencimentoRegistro":"2010-07-01T00:00:00.000-0300","principioAtivo":null,"situacaoApresentacao":"Caduco/Cancelado","dataRegistro":"2000-07-13T00:00:00.000-0300","categoriaRegulatoria":{"codigo":8,"descricao":"Similar"},"medicamentoReferencia":null,"categoriaProduto":null,"tipoAutorizacao":"REGISTRADO","acancelar":false,"mesAnoVencimentoFormatado":"07/2010","numeroRegistroFormatado":"104300025"},"empresa":{"cnpj":"42457796000156","razaoSocial":"DIFFUCAP - CHEMOBRÁS QUÍMICA E FARMACÊUTICA LTDA","numeroAutorizacao":"1004304","cnpjFormatado":"42.457.796/0001-56"},"processo":{"numero":"250000158599976","situacao":29,"numeroProcessoFormatado":"25000.015859/99-76"}},{"ordem":26,"produto":{"codigo":4230,"nome":"PRONAZOL","numeroRegistro":"104300013","tipo":{"codigo":1,"descricao":null},"categoria":null,"situacaoRotulo":null,"dataVencimento":null,"mesAnoVencimento":"062029","dataVencimentoRegistro":"2029-06-01T00:00:00.000-0300","principioAtivo":"FLUCONAZOL","situacaoApresentacao":"Válido","dataRegistro":"1998-02-17T00:00:00.000-0300","categoriaRegulatoria":{"codigo":8,"descricao":"Similar"},"medicamentoReferencia":"ZOLTEC","categoriaProduto":null,"tipoAutorizacao":"REGISTRADO","acancelar":false,"mesAnoVencimentoFormatado":"06/2029","numeroRegistroFormatado":"104300013"},"empresa":{"cnpj":"42457796000156","razaoSocial":"DIFFUCAP - CHEMOBRÁS QUÍMICA E FARMACÊUTICA LTDA","numeroAutorizacao":"1004304","cnpjFormatado":"42.457.796/0001-56"},"processo":{"numero":"250000076929310","situacao":29,"numeroProcessoFormatado":"25000.007692/93-10"}},{"ordem":27,"produto":{"codigo":374643,"nome":"RINO-ATINAC","numeroRegistro":"104300039","tipo":{"codigo":1,"descricao":null},"categoria":null,"situacaoRotulo":null,"dataVencimento":null,"mesAnoVencimento":"012013","dataVencimentoRegistro":"2013-01-01T00:00:00.000-0300","principioAtivo":null,"situacaoApresentacao":"Caduco/Cancelado","dataRegistro":"2006-03-20T00:00:00.000-0300","categoriaRegulatoria":{"codigo":8,"descricao":"Similar"},"medicamentoReferencia":null,"categoriaProduto":null,"tipoAutorizacao":"REGISTRADO","acancelar":false,"mesAnoVencimentoFormatado":"01/2013","numeroRegistroFormatado":"104300039"},"empresa":{"cnpj":"42457796000156","razaoSocial":"DIFFUCAP - CHEMOBRÁS QUÍMICA E FARMACÊUTICA LTDA","numeroAutorizacao":"1004304","cnpjFormatado":"42.457.796/0001-56"},"processo":{"numero":"250000085909296","situacao":31,"numeroProcessoFormatado":"25000.008590/92-96"}},{"ordem":28,"produto":{"codigo":7904,"nome":"TEOSIN","numeroRegistro":"104300033","tipo":{"codigo":1,"descricao":null},"categoria":null,"situacaoRotulo":null,"dataVencimento":null,"mesAnoVencimento":"012007","dataVencimentoRegistro":"2007-01-01T00:00:00.000-0300","principioAtivo":null,"situacaoApresentacao":"Caduco/Cancelado","dataRegistro":"2002-01-30T00:00:00.000-0200","categoriaRegulatoria":{"codigo":8,"descricao":"Similar"},"medicamentoReferencia":null,"categoriaProduto":null,"tipoAutorizacao":"REGISTRADO","acancelar":false,"mesAnoVencimentoFormatado":"01/2007","numeroRegistroFormatado":"104300033"},"empresa":{"cnpj":"42457796000156","razaoSocial":"DIFFUCAP - CHEMOBRÁS QUÍMICA E FARMACÊUTICA LTDA","numeroAutorizacao":"1004304","cnpjFormatado":"42.457.796/0001-56"},"processo":{"numero":"250000268959730","situacao":29,"numeroProcessoFormatado":"25000.026895/97-30"}},{"ordem":29,"produto":{"codigo":5393,"nome":"TONOTENSIN","numeroRegistro":"104300022","tipo":{"codigo":1,"descricao":null},"categoria":null,"situacaoRotulo":null,"dataVencimento":null,"mesAnoVencimento":"062005","dataVencimentoRegistro":"2005-06-01T00:00:00.000-0300","principioAtivo":null,"situacaoApresentacao":"Caduco/Cancelado","dataRegistro":"2000-06-23T00:00:00.000-0300","categoriaRegulatoria":{"codigo":8,"descricao":"Similar"},"medicamentoReferencia":null,"categoriaProduto":null,"tipoAutorizacao":"REGISTRADO","acancelar":false,"mesAnoVencimentoFormatado":"06/2005","numeroRegistroFormatado":"104300022"},"empresa":{"cnpj":"42457796000156","razaoSocial":"DIFFUCAP - CHEMOBRÁS QUÍMICA E FARMACÊUTICA LTDA","numeroAutorizacao":"1004304","cnpjFormatado":"42.457.796/0001-56"},"processo":{"numero":"250000241829452","situacao":29,"numeroProcessoFormatado":"25000.024182/94-52"}},{"ordem":30,"produto":{"codigo":276029,"nome":"ULCESTOP","numeroRegistro":"104300036","tipo":{"codigo":1,"descricao":null},"categoria":null,"situacaoRotulo":null,"dataVencimento":null,"mesAnoVencimento":"052023","dataVencimentoRegistro":"2023-05-01T00:00:00.000-0300","principioAtivo":null,"situacaoApresentacao":"Caduco/Cancelado","dataRegistro":"2003-05-27T00:00:00.000-0300","categoriaRegulatoria":{"codigo":8,"descricao":"Similar"},"medicamentoReferencia":null,"categoriaProduto":null,"tipoAutorizacao":"REGISTRADO","acancelar":false,"mesAnoVencimentoFormatado":"05/2023","numeroRegistroFormatado":"104300036"},"empresa":{"cnpj":"42457796000156","razaoSocial":"DIFFUCAP - CHEMOBRÁS QUÍMICA E FARMACÊUTICA LTDA","numeroAutorizacao":"1004304","cnpjFormatado":"42.457.796/0001-56"},"processo":{"numero":"250000192589805","situacao":29,"numeroProcessoFormatado":"25000.019258/98-05"}},{"ordem":31,"produto":{"codigo":1299318,"nome":"UNAK","numeroRegistro":"104300043","tipo":{"codigo":1,"descricao":null},"categoria":null,"situacaoRotulo":null,"dataVencimento":null,"mesAnoVencimento":"012029","dataVencimentoRegistro":"2029-01-01T00:00:00.000-0300","principioAtivo":"SINVASTATINA","situacaoApresentacao":"Válido","dataRegistro":"2019-01-14T00:00:00.000-0300","categoriaRegulatoria":{"codigo":8,"descricao":"Similar"},"medicamentoReferencia":"ZOCOR","categoriaProduto":null,"tipoAutorizacao":"REGISTRADO","acancelar":false,"mesAnoVencimentoFormatado":"01/2029","numeroRegistroFormatado":"104300043"},"empresa":{"cnpj":"42457796000156","razaoSocial":"DIFFUCAP - CHEMOBRÁS QUÍMICA E FARMACÊUTICA LTDA","numeroAutorizacao":"1004304","cnpjFormatado":"42.457.796/0001-56"},"processo":{"numero":"25351390581201849","situacao":29,"numeroProcessoFormatado":"25351.390581/2018-49"}},{"ordem":32,"produto":{"codigo":5507,"nome":"Winter AP","numeroRegistro":"104300027","tipo":{"codigo":1,"descricao":null},"categoria":null,"situacaoRotulo":null,"dataVencimento":null,"mesAnoVencimento":"102025","dataVencimentoRegistro":"2025-10-01T00:00:00.000-0300","principioAtivo":null,"situacaoApresentacao":"Válido","dataRegistro":"2000-10-25T00:00:00.000-0300","categoriaRegulatoria":{"codigo":8,"descricao":"Similar"},"medicamentoReferencia":null,"categoriaProduto":null,"tipoAutorizacao":"REGISTRADO","acancelar":false,"mesAnoVencimentoFormatado":"10/2025","numeroRegistroFormatado":"104300027"},"empresa":{"cnpj":"42457796000156","razaoSocial":"DIFFUCAP - CHEMOBRÁS QUÍMICA E FARMACÊUTICA LTDA","numeroAutorizacao":"1004304","cnpjFormatado":"42.457.796/0001-56"},"processo":{"numero":"250000109488864","situacao":29,"numeroProcessoFormatado":"25000.010948/88-64"}}],"totalElements":32,"totalPages":1,"last":true,"numberOfElements":32,"first":true,"sort":null,"size":1000,"number":0}