{"content":[{"ordem":1,"produto":{"codigo":366827,"nome":"ACTICALCIN","numeroRegistro":"103410001","tipo":{"codigo":1,"descricao":null},"categoria":null,"situacaoRotulo":null,"dataVencimento":null,"mesAnoVencimento":"052009","dataVencimentoRegistro":"2009-05-01T00:00:00.000-0300","principioAtivo":null,"situacaoApresentacao":"Caduco/Cancelado","dataRegistro":"1989-11-07T00:00:00.000-0200","categoriaRegulatoria":{"codigo":8,"descricao":"Similar"},"medicamentoReferencia":null,"categoriaProduto":null,"tipoAutorizacao":"REGISTRADO","acancelar":false,"mesAnoVencimentoFormatado":"05/2009","numeroRegistroFormatado":"103410001"},"empresa":{"cnpj":"61455192000115","razaoSocial":"TRB PHARMA INDÚSTRIA QUÍMICA E FARMACÊUTICA LTDA","numeroAutorizacao":"1003417","cnpjFormatado":"61.455.192/0001-15"},"processo":{"numero":"250000167228802","situacao":29,"numeroProcessoFormatado":"25000.016722/88-02"}},{"ordem":2,"produto":{"codigo":165203,"nome":"ARTISAL","numeroRegistro":"103410002","tipo":{"codigo":1,"descricao":null},"categoria":null,"situacaoRotulo":null,"dataVencimento":null,"mesAnoVencimento":"102027","dataVencimentoRegistro":"2027-10-01T00:00:00.000-0300","principioAtivo":null,"situacaoApresentacao":"Válido","dataRegistro":"2002-10-02T00:00:00.000-0300","categoriaRegulatoria":{"codigo":8,"descricao":"Similar"},"medicamentoReferencia":null,"categoriaProduto":null,"tipoAutorizacao":"REGISTRADO","acancelar":false,"mesAnoVencimentoFormatado":"10/2027","numeroRegistroFormatado":"103410002"},"empresa":{"cnpj":"61455192000115","razaoSocial":"TRB PHARMA INDÚSTRIA QUÍMICA E FARMACÊUTICA LTDA","numeroAutorizacao":"1003417","cnpjFormatado":"61.455.192/0001-15"},"processo":{"numero":"2500101390184","situacao":29,"numeroProcessoFormatado":"25001.013901/84"}},{"ordem":3,"produto":{"codigo":125473,"nome":"ARTRODAR","numeroRegistro":"103410052","tipo":{"codigo":1,"descricao":null},"categoria":null,"situacaoRotulo":null,"dataVencimento":"2026-09-02T00:00:00.000-0300","mesAnoVencimento":"122025","dataVencimentoRegistro":"2025-12-01T00:00:00.000-0300","principioAtivo":"DIACEREÍNA","situacaoApresentacao":"Válido","dataRegistro":"2002-04-24T00:00:00.000-0300","categoriaRegulatoria":{"codigo":6,"descricao":"Novo"},"medicamentoReferencia":null,"categoriaProduto":null,"tipoAutorizacao":"REGISTRADO","acancelar":false,"mesAnoVencimentoFormatado":"12/2025","numeroRegistroFormatado":"103410052"},"empresa":{"cnpj":"61455192000115","razaoSocial":"TRB PHARMA INDÚSTRIA QUÍMICA E FARMACÊUTICA LTDA","numeroAutorizacao":"1003417","cnpjFormatado":"61.455.192/0001-15"},"processo":{"numero":"250000208159354","situacao":29,"numeroProcessoFormatado":"25000.020815/93-54"}},{"ordem":4,"produto":{"codigo":4332,"nome":"BROS","numeroRegistro":"103410005","tipo":{"codigo":1,"descricao":null},"categoria":null,"situacaoRotulo":null,"dataVencimento":null,"mesAnoVencimento":"042011","dataVencimentoRegistro":"2011-04-01T00:00:00.000-0300","principioAtivo":null,"situacaoApresentacao":"Caduco/Cancelado","dataRegistro":"2001-05-07T00:00:00.000-0300","categoriaRegulatoria":{"codigo":6,"descricao":"Novo"},"medicamentoReferencia":null,"categoriaProduto":null,"tipoAutorizacao":"REGISTRADO","acancelar":false,"mesAnoVencimentoFormatado":"04/2011","numeroRegistroFormatado":"103410005"},"empresa":{"cnpj":"61455192000115","razaoSocial":"TRB PHARMA INDÚSTRIA QUÍMICA E FARMACÊUTICA LTDA","numeroAutorizacao":"1003417","cnpjFormatado":"61.455.192/0001-15"},"processo":{"numero":"2500102700084","situacao":29,"numeroProcessoFormatado":"25001.027000/84"}},{"ordem":5,"produto":{"codigo":607,"nome":"CLEVERON","numeroRegistro":"103410055","tipo":{"codigo":1,"descricao":null},"categoria":null,"situacaoRotulo":null,"dataVencimento":null,"mesAnoVencimento":"012013","dataVencimentoRegistro":"2013-01-01T00:00:00.000-0300","principioAtivo":null,"situacaoApresentacao":"Caduco/Cancelado","dataRegistro":"1998-01-16T00:00:00.000-0300","categoriaRegulatoria":{"codigo":8,"descricao":"Similar"},"medicamentoReferencia":null,"categoriaProduto":null,"tipoAutorizacao":"REGISTRADO","acancelar":false,"mesAnoVencimentoFormatado":"01/2013","numeroRegistroFormatado":"103410055"},"empresa":{"cnpj":"61455192000115","razaoSocial":"TRB PHARMA INDÚSTRIA QUÍMICA E FARMACÊUTICA LTDA","numeroAutorizacao":"1003417","cnpjFormatado":"61.455.192/0001-15"},"processo":{"numero":"250000167839780","situacao":29,"numeroProcessoFormatado":"25000.016783/97-80"}},{"ordem":6,"produto":{"codigo":2865,"nome":"CLORIDRATO DE SELEGILINA","numeroRegistro":"103410054","tipo":{"codigo":1,"descricao":null},"categoria":null,"situacaoRotulo":null,"dataVencimento":null,"mesAnoVencimento":"032002","dataVencimentoRegistro":"2002-03-01T00:00:00.000-0300","principioAtivo":null,"situacaoApresentacao":"Caduco/Cancelado","dataRegistro":"1997-03-11T00:00:00.000-0300","categoriaRegulatoria":{"codigo":8,"descricao":"Similar"},"medicamentoReferencia":null,"categoriaProduto":null,"tipoAutorizacao":"REGISTRADO","acancelar":false,"mesAnoVencimentoFormatado":"03/2002","numeroRegistroFormatado":"103410054"},"empresa":{"cnpj":"61455192000115","razaoSocial":"TRB PHARMA INDÚSTRIA QUÍMICA E FARMACÊUTICA LTDA","numeroAutorizacao":"1003417","cnpjFormatado":"61.455.192/0001-15"},"processo":{"numero":"250000350329663","situacao":29,"numeroProcessoFormatado":"25000.035032/96-63"}},{"ordem":7,"produto":{"codigo":519483,"nome":"DICIPER","numeroRegistro":"103410018","tipo":{"codigo":1,"descricao":null},"categoria":null,"situacaoRotulo":null,"dataVencimento":null,"mesAnoVencimento":"101996","dataVencimentoRegistro":"1996-10-01T00:00:00.000-0300","principioAtivo":null,"situacaoApresentacao":"Caduco/Cancelado","dataRegistro":"1978-12-03T00:00:00.000-0300","categoriaRegulatoria":{"codigo":8,"descricao":"Similar"},"medicamentoReferencia":null,"categoriaProduto":null,"tipoAutorizacao":"REGISTRADO","acancelar":false,"mesAnoVencimentoFormatado":"10/1996","numeroRegistroFormatado":"103410018"},"empresa":{"cnpj":"61455192000115","razaoSocial":"TRB PHARMA INDÚSTRIA QUÍMICA E FARMACÊUTICA LTDA","numeroAutorizacao":"1003417","cnpjFormatado":"61.455.192/0001-15"},"processo":{"numero":"2500101030378","situacao":29,"numeroProcessoFormatado":"25001.010303/78"}},{"ordem":8,"produto":{"codigo":519020,"nome":"EPACTIV B12","numeroRegistro":"103410061","tipo":{"codigo":1,"descricao":null},"categoria":null,"situacaoRotulo":null,"dataVencimento":null,"mesAnoVencimento":"101994","dataVencimentoRegistro":"1994-10-01T00:00:00.000-0300","principioAtivo":null,"situacaoApresentacao":"Caduco/Cancelado","dataRegistro":"1984-06-28T00:00:00.000-0300","categoriaRegulatoria":{"codigo":8,"descricao":"Similar"},"medicamentoReferencia":null,"categoriaProduto":null,"tipoAutorizacao":"REGISTRADO","acancelar":false,"mesAnoVencimentoFormatado":"10/1994","numeroRegistroFormatado":"103410061"},"empresa":{"cnpj":"61455192000115","razaoSocial":"TRB PHARMA INDÚSTRIA QUÍMICA E FARMACÊUTICA LTDA","numeroAutorizacao":"1003417","cnpjFormatado":"61.455.192/0001-15"},"processo":{"numero":"2500100548539","situacao":29,"numeroProcessoFormatado":"25001.005485/39"}},{"ordem":9,"produto":{"codigo":472268,"nome":"ESTROTHELINA","numeroRegistro":"103410060","tipo":{"codigo":1,"descricao":null},"categoria":null,"situacaoRotulo":null,"dataVencimento":null,"mesAnoVencimento":"062012","dataVencimentoRegistro":"2012-06-01T00:00:00.000-0300","principioAtivo":null,"situacaoApresentacao":"Caduco/Cancelado","dataRegistro":"1985-11-14T00:00:00.000-0200","categoriaRegulatoria":{"codigo":8,"descricao":"Similar"},"medicamentoReferencia":null,"categoriaProduto":null,"tipoAutorizacao":"REGISTRADO","acancelar":false,"mesAnoVencimentoFormatado":"06/2012","numeroRegistroFormatado":"103410060"},"empresa":{"cnpj":"61455192000115","razaoSocial":"TRB PHARMA INDÚSTRIA QUÍMICA E FARMACÊUTICA LTDA","numeroAutorizacao":"1003417","cnpjFormatado":"61.455.192/0001-15"},"processo":{"numero":"2500100875840","situacao":29,"numeroProcessoFormatado":"25001.008758/40"}},{"ordem":10,"produto":{"codigo":518255,"nome":"GYNECOLINA","numeroRegistro":"103410030","tipo":{"codigo":1,"descricao":null},"categoria":null,"situacaoRotulo":null,"dataVencimento":null,"mesAnoVencimento":"052012","dataVencimentoRegistro":"2012-05-01T00:00:00.000-0300","principioAtivo":null,"situacaoApresentacao":"Caduco/Cancelado","dataRegistro":"1980-09-22T00:00:00.000-0300","categoriaRegulatoria":{"codigo":8,"descricao":"Similar"},"medicamentoReferencia":null,"categoriaProduto":null,"tipoAutorizacao":"REGISTRADO","acancelar":false,"mesAnoVencimentoFormatado":"05/2012","numeroRegistroFormatado":"103410030"},"empresa":{"cnpj":"61455192000115","razaoSocial":"TRB PHARMA INDÚSTRIA QUÍMICA E FARMACÊUTICA LTDA","numeroAutorizacao":"1003417","cnpjFormatado":"61.455.192/0001-15"},"processo":{"numero":"2599100818580","situacao":29,"numeroProcessoFormatado":"25991.008185/80"}},{"ordem":11,"produto":{"codigo":454174,"nome":"HEPATO DELFIN","numeroRegistro":"103410014","tipo":{"codigo":1,"descricao":null},"categoria":null,"situacaoRotulo":null,"dataVencimento":null,"mesAnoVencimento":"092004","dataVencimentoRegistro":"2004-09-01T00:00:00.000-0300","principioAtivo":null,"situacaoApresentacao":"Caduco/Cancelado","dataRegistro":"2006-04-10T00:00:00.000-0300","categoriaRegulatoria":{"codigo":4,"descricao":"Fitoterápico"},"medicamentoReferencia":null,"categoriaProduto":null,"tipoAutorizacao":"REGISTRADO","acancelar":false,"mesAnoVencimentoFormatado":"09/2004","numeroRegistroFormatado":"103410014"},"empresa":{"cnpj":"61455192000115","razaoSocial":"TRB PHARMA INDÚSTRIA QUÍMICA E FARMACÊUTICA LTDA","numeroAutorizacao":"1003417","cnpjFormatado":"61.455.192/0001-15"},"processo":{"numero":"2500100698037","situacao":29,"numeroProcessoFormatado":"25001.006980/37"}},{"ordem":12,"produto":{"codigo":466,"nome":"HYALUDERMIN","numeroRegistro":"103410053","tipo":{"codigo":1,"descricao":null},"categoria":null,"situacaoRotulo":null,"dataVencimento":null,"mesAnoVencimento":"042026","dataVencimentoRegistro":"2026-04-01T00:00:00.000-0300","principioAtivo":"ÁCIDO HIALURÔNICO","situacaoApresentacao":"Válido","dataRegistro":"1996-04-01T00:00:00.000-0300","categoriaRegulatoria":{"codigo":8,"descricao":"Similar"},"medicamentoReferencia":null,"categoriaProduto":null,"tipoAutorizacao":"REGISTRADO","acancelar":false,"mesAnoVencimentoFormatado":"04/2026","numeroRegistroFormatado":"103410053"},"empresa":{"cnpj":"61455192000115","razaoSocial":"TRB PHARMA INDÚSTRIA QUÍMICA E FARMACÊUTICA LTDA","numeroAutorizacao":"1003417","cnpjFormatado":"61.455.192/0001-15"},"processo":{"numero":"250000010579078","situacao":29,"numeroProcessoFormatado":"25000.001057/90-78"}},{"ordem":13,"produto":{"codigo":5662,"nome":"METHYCOBAL","numeroRegistro":"103410056","tipo":{"codigo":1,"descricao":null},"categoria":null,"situacaoRotulo":null,"dataVencimento":null,"mesAnoVencimento":"092015","dataVencimentoRegistro":"2015-09-01T00:00:00.000-0300","principioAtivo":null,"situacaoApresentacao":"Caduco/Cancelado","dataRegistro":"2000-09-01T00:00:00.000-0300","categoriaRegulatoria":{"codigo":6,"descricao":"Novo"},"medicamentoReferencia":null,"categoriaProduto":null,"tipoAutorizacao":"REGISTRADO","acancelar":false,"mesAnoVencimentoFormatado":"09/2015","numeroRegistroFormatado":"103410056"},"empresa":{"cnpj":"61455192000115","razaoSocial":"TRB PHARMA INDÚSTRIA QUÍMICA E FARMACÊUTICA LTDA","numeroAutorizacao":"1003417","cnpjFormatado":"61.455.192/0001-15"},"processo":{"numero":"250000207139970","situacao":29,"numeroProcessoFormatado":"25000.020713/99-70"}},{"ordem":14,"produto":{"codigo":125796,"nome":"POLIREUMIN","numeroRegistro":"103410043","tipo":{"codigo":1,"descricao":null},"categoria":null,"situacaoRotulo":null,"dataVencimento":null,"mesAnoVencimento":"082028","dataVencimentoRegistro":"2028-08-01T00:00:00.000-0300","principioAtivo":"HIALURONATO DE SÓDIO","situacaoApresentacao":"Válido","dataRegistro":"2002-05-22T00:00:00.000-0300","categoriaRegulatoria":{"codigo":6,"descricao":"Novo"},"medicamentoReferencia":null,"categoriaProduto":null,"tipoAutorizacao":"REGISTRADO","acancelar":false,"mesAnoVencimentoFormatado":"08/2028","numeroRegistroFormatado":"103410043"},"empresa":{"cnpj":"61455192000115","razaoSocial":"TRB PHARMA INDÚSTRIA QUÍMICA E FARMACÊUTICA LTDA","numeroAutorizacao":"1003417","cnpjFormatado":"61.455.192/0001-15"},"processo":{"numero":"2599202558076","situacao":29,"numeroProcessoFormatado":"25992.025580/76"}},{"ordem":15,"produto":{"codigo":716435,"nome":"SICOTRAT","numeroRegistro":"103410062","tipo":{"codigo":1,"descricao":null},"categoria":null,"situacaoRotulo":null,"dataVencimento":null,"mesAnoVencimento":"112019","dataVencimentoRegistro":"2019-11-01T00:00:00.000-0300","principioAtivo":null,"situacaoApresentacao":"Caduco/Cancelado","dataRegistro":"1991-07-17T00:00:00.000-0300","categoriaRegulatoria":{"codigo":1,"descricao":"Biológico"},"medicamentoReferencia":null,"categoriaProduto":null,"tipoAutorizacao":"REGISTRADO","acancelar":false,"mesAnoVencimentoFormatado":"11/2019","numeroRegistroFormatado":"103410062"},"empresa":{"cnpj":"61455192000115","razaoSocial":"TRB PHARMA INDÚSTRIA QUÍMICA E FARMACÊUTICA LTDA","numeroAutorizacao":"1003417","cnpjFormatado":"61.455.192/0001-15"},"processo":{"numero":"250000167258892","situacao":29,"numeroProcessoFormatado":"25000.016725/88-92"}},{"ordem":16,"produto":{"codigo":276623,"nome":"SINAXIAL","numeroRegistro":"103410004","tipo":{"codigo":1,"descricao":null},"categoria":null,"situacaoRotulo":null,"dataVencimento":null,"mesAnoVencimento":"062010","dataVencimentoRegistro":"2010-06-01T00:00:00.000-0300","principioAtivo":null,"situacaoApresentacao":"Caduco/Cancelado","dataRegistro":"1979-10-30T00:00:00.000-0300","categoriaRegulatoria":{"codigo":1,"descricao":"Biológico"},"medicamentoReferencia":null,"categoriaProduto":null,"tipoAutorizacao":"REGISTRADO","acancelar":false,"mesAnoVencimentoFormatado":"06/2010","numeroRegistroFormatado":"103410004"},"empresa":{"cnpj":"61455192000115","razaoSocial":"TRB PHARMA INDÚSTRIA QUÍMICA E FARMACÊUTICA LTDA","numeroAutorizacao":"1003417","cnpjFormatado":"61.455.192/0001-15"},"processo":{"numero":"2599100174279","situacao":29,"numeroProcessoFormatado":"25991.001742/79"}},{"ordem":17,"produto":{"codigo":276429,"nome":"SYGEN","numeroRegistro":"103410003","tipo":{"codigo":1,"descricao":null},"categoria":null,"situacaoRotulo":null,"dataVencimento":null,"mesAnoVencimento":"062030","dataVencimentoRegistro":"2030-06-01T00:00:00.000-0300","principioAtivo":"MONOSSIALOGANGLIOSIDEO","situacaoApresentacao":"Válido","dataRegistro":"1991-11-18T00:00:00.000-0300","categoriaRegulatoria":{"codigo":1,"descricao":"Biológico"},"medicamentoReferencia":null,"categoriaProduto":null,"tipoAutorizacao":"REGISTRADO","acancelar":false,"mesAnoVencimentoFormatado":"06/2030","numeroRegistroFormatado":"103410003"},"empresa":{"cnpj":"61455192000115","razaoSocial":"TRB PHARMA INDÚSTRIA QUÍMICA E FARMACÊUTICA LTDA","numeroAutorizacao":"1003417","cnpjFormatado":"61.455.192/0001-15"},"processo":{"numero":"2500102678084","situacao":29,"numeroProcessoFormatado":"25001.026780/84"}},{"ordem":18,"produto":{"codigo":698099,"nome":"TELEXIAL","numeroRegistro":"103410063","tipo":{"codigo":1,"descricao":null},"categoria":null,"situacaoRotulo":null,"dataVencimento":null,"mesAnoVencimento":"112014","dataVencimentoRegistro":"2014-11-01T00:00:00.000-0300","principioAtivo":null,"situacaoApresentacao":"Caduco/Cancelado","dataRegistro":"1987-10-08T00:00:00.000-0300","categoriaRegulatoria":{"codigo":1,"descricao":"Biológico"},"medicamentoReferencia":null,"categoriaProduto":null,"tipoAutorizacao":"REGISTRADO","acancelar":false,"mesAnoVencimentoFormatado":"11/2014","numeroRegistroFormatado":"103410063"},"empresa":{"cnpj":"61455192000115","razaoSocial":"TRB PHARMA INDÚSTRIA QUÍMICA E FARMACÊUTICA LTDA","numeroAutorizacao":"1003417","cnpjFormatado":"61.455.192/0001-15"},"processo":{"numero":"2599100418281","situacao":29,"numeroProcessoFormatado":"25991.004182/81"}},{"ordem":19,"produto":{"codigo":472219,"nome":"VERAPAN","numeroRegistro":"103411050","tipo":{"codigo":1,"descricao":null},"categoria":null,"situacaoRotulo":null,"dataVencimento":null,"mesAnoVencimento":"102004","dataVencimentoRegistro":"2004-10-01T00:00:00.000-0300","principioAtivo":null,"situacaoApresentacao":"Caduco/Cancelado","dataRegistro":"1984-08-23T00:00:00.000-0300","categoriaRegulatoria":{"codigo":8,"descricao":"Similar"},"medicamentoReferencia":null,"categoriaProduto":null,"tipoAutorizacao":"REGISTRADO","acancelar":false,"mesAnoVencimentoFormatado":"10/2004","numeroRegistroFormatado":"103411050"},"empresa":{"cnpj":"61455192000115","razaoSocial":"TRB PHARMA INDÚSTRIA QUÍMICA E FARMACÊUTICA LTDA","numeroAutorizacao":"1003417","cnpjFormatado":"61.455.192/0001-15"},"processo":{"numero":"2500100453472","situacao":29,"numeroProcessoFormatado":"25001.004534/72"}}],"totalElements":19,"totalPages":1,"last":true,"numberOfElements":19,"first":true,"sort":null,"size":1000,"number":0}